{"Rk": "1", "Player": "Marty Conlon", "Age": "24", "Team": "SEA", "Pos": "C", "G": "1", "GS": "0", "MP": "1", "FG": "0.0", "FGA": "36.0", "FG%": ".000", "3P": "0.0", "3PA": "0.0", "3P%": "", "2P": "0.0", "2PA": "36.0", "2P%": ".000", "eFG%": ".000", "FT": "72.0", "FTA": "72.0", "FT%": "1.000", "ORB": "0.0", "DRB": "36.0", "TRB": "36.0", "AST": "0.0", "STL": "0.0", "BLK": "0.0", "TOV": "0.0", "PF": "0.0", "PTS": "72.0", "Awards": ""}{"Rk": "2", "Player": "John Morton", "Age": "24", "Team": "MIA", "Pos": "SF", "G": "1", "GS": "0", "MP": "2", "FG": "0.0", "FGA": "0.0", "FG%": "", "3P": "0.0", "3PA": "0.0", "3P%": "", "2P": "0.0", "2PA": "0.0", "2P%": "", "eFG%": "", "FT": "36.0", "FTA": "36.0", "FT%": "1.000", "ORB": "0.0", "DRB": "0.0", "TRB": "0.0", "AST": "0.0", "STL": "0.0", "BLK": "0.0", "TOV": "18.0", "PF": "0.0", "PTS": "36.0", "Awards": ""}{"Rk": "3", "Player": "Bobby Phills", "Age": "22", "Team": "CLE", "Pos": "SG", "G": "5", "GS": "0", "MP": "12", "FG": "12.0", "FGA": "27.0", "FG%": ".444", "3P": "0.0", "3PA": "3.0", "3P%": ".000", "2P": "12.0", "2PA": "24.0", "2P%": ".500", "eFG%": ".444", "FT": "9.0", "FTA": "12.0", "FT%": ".750", "ORB": "6.0", "DRB": "12.0", "TRB": "18.0", "AST": "15.0", "STL": "3.0", "BLK": "0.0", "TOV": "6.0", "PF": "3.0", "PTS": "33.0", "Awards": ""}{"Rk": "4", "Player": "Corey Crowder", "Age": "22", "Team": "UTA", "Pos": "SF", "G": "4", "GS": "0", "MP": "12", "FG": "15.0", "FGA": "27.0", "FG%": ".556", "3P": "0.0", "3PA": "6.0", "3P%": ".000", "2P": "15.0", "2PA": "21.0", "2P%": ".714", "eFG%": ".556", "FT": "0.0", "FTA": "3.0", "FT%": ".000", "ORB": "3.0", "DRB": "3.0", "TRB": "6.0", "AST": "3.0", "STL": "3.0", "BLK": "0.0", "TOV": "6.0", "PF": "3.0", "PTS": "30.0", "Awards": ""}{"Rk": "5", "Player": "Michael Jordan", "Age": "28", "Team": "CHI", "Pos": "SG", "G": "22", "GS": "22", "MP": "920", "FG": "11.3", "FGA": "22.7", "FG%": ".499", "3P": "0.7", "3PA": "1.7", "3P%": ".386", "2P": "10.7", "2PA": "21.0", "2P%": ".508", "eFG%": ".514", "FT": "6.3", "FTA": "7.4", "FT%": ".857", "ORB": "1.4", "DRB": "3.9", "TRB": "5.4", "AST": "5.0", "STL": "1.7", "BLK": "0.6", "TOV": "3.2", "PF": "2.4", "PTS": "29.7", "Awards": "Finals MVP-1"}{"Rk": "6", "Player": "Eric Murdock", "Age": "23", "Team": "UTA", "Pos": "PG", "G": "3", "GS": "0", "MP": "11", "FG": "9.8", "FGA": "16.4", "FG%": ".600", "3P": "0.0", "3PA": "3.3", "3P%": ".000", "2P": "9.8", "2PA": "13.1", "2P%": ".750", "eFG%": ".600", "FT": "6.5", "FTA": "6.5", "FT%": "1.000", "ORB": "0.0", "DRB": "9.8", "TRB": "9.8", "AST": "3.3", "STL": "3.3", "BLK": "3.3", "TOV": "9.8", "PF": "3.3", "PTS": "26.2", "Awards": ""}{"Rk": "7", "Player": "Reggie Lewis", "Age": "26", "Team": "BOS", "Pos": "SG", "G": "10", "GS": "10", "MP": "408", "FG": "10.1", "FGA": "19.2", "FG%": ".528", "3P": "0.2", "3PA": "0.5", "3P%": ".333", "2P": "10.0", "2PA": "18.7", "2P%": ".533", "eFG%": ".532", "FT": "4.2", "FTA": "5.6", "FT%": ".762", "ORB": "1.0", "DRB": "2.8", "TRB": "3.8", "AST": "3.4", "STL": "2.1", "BLK": "0.7", "TOV": "1.4", "PF": "3.4", "PTS": "24.7", "Awards": ""}{"Rk": "8", "Player": "Karl Malone", "Age": "28", "Team": "UTA", "Pos": "PF", "G": "16", "GS": "16", "MP": "688", "FG": "7.7", "FGA": "14.9", "FG%": ".521", "3P": "0.0", "3PA": "0.1", "3P%": ".000", "2P": "7.7", "2PA": "14.8", "2P%": ".525", "eFG%": ".521", "FT": "8.8", "FTA": "11.0", "FT%": ".805", "ORB": "2.3", "DRB": "7.2", "TRB": "9.5", "AST": "2.2", "STL": "1.2", "BLK": "1.0", "TOV": "2.4", "PF": "3.0", "PTS": "24.3", "Awards": ""}{"Rk": "9", "Player": "Eddie Johnson", "Age": "32", "Team": "SEA", "Pos": "SF", "G": "9", "GS": "0", "MP": "247", "FG": "9.5", "FGA": "20.0", "FG%": ".474", "3P": "0.6", "3PA": "3.2", "3P%": ".182", "2P": "8.9", "2PA": "16.8", "2P%": ".530", "eFG%": ".489", "FT": "4.7", "FTA": "5.0", "FT%": ".941", "ORB": "1.2", "DRB": "2.8", "TRB": "3.9", "AST": "1.2", "STL": "0.4", "BLK": "0.4", "TOV": "2.2", "PF": "2.8", "PTS": "24.2", "Awards": ""}{"Rk": "10", "Player": "William Bedford", "Age": "28", "Team": "DET", "Pos": "C", "G": "1", "GS": "0", "MP": "9", "FG": "12.0", "FGA": "24.0", "FG%": ".500", "3P": "0.0", "3PA": "0.0", "3P%": "", "2P": "12.0", "2PA": "24.0", "2P%": ".500", "eFG%": ".500", "FT": "0.0", "FTA": "0.0", "FT%": "", "ORB": "0.0", "DRB": "8.0", "TRB": "8.0", "AST": "0.0", "STL": "4.0", "BLK": "0.0", "TOV": "0.0", "PF": "4.0", "PTS": "24.0", "Awards": ""}{"Rk": "11", "Player": "Dave Feitl", "Age": "29", "Team": "NJN", "Pos": "C", "G": "1", "GS": "0", "MP": "3", "FG": "12.0", "FGA": "24.0", "FG%": ".500", "3P": "0.0", "3PA": "0.0", "3P%": "", "2P": "12.0", "2PA": "24.0", "2P%": ".500", "eFG%": ".500", "FT": "0.0", "FTA": "0.0", "FT%": "", "ORB": "0.0", "DRB": "12.0", "TRB": "12.0", "AST": "0.0", "STL": "0.0", "BLK": "0.0", "TOV": "12.0", "PF": "0.0", "PTS": "24.0", "Awards": ""}{"Rk": "12", "Player": "Stojko Vrankovi\u0107", "Age": "28", "Team": "BOS", "Pos": "C", "G": "1", "GS": "0", "MP": "3", "FG": "12.0", "FGA": "12.0", "FG%": "1.000", "3P": "0.0", "3PA": "0.0", "3P%": "", "2P": "12.0", "2PA": "12.0", "2P%": "1.000", "eFG%": "1.000", "FT": "0.0", "FTA": "0.0", "FT%": "", "ORB": "0.0", "DRB": "0.0", "TRB": "0.0", "AST": "12.0", "STL": "0.0", "BLK": "0.0", "TOV": "0.0", "PF": "0.0", "PTS": "24.0", "Awards": ""}{"Rk": "13", "Player": "Clyde Drexler", "Age": "29", "Team": "POR", "Pos": "SG", "G": "21", "GS": "21", "MP": "847", "FG": "8.4", "FGA": "18.1", "FG%": ".466", "3P": "0.8", "3PA": "3.4", "3P%": ".235", "2P": "7.6", "2PA": "14.6", "2P%": ".520", "eFG%": ".488", "FT": "5.9", "FTA": "7.3", "FT%": ".807", "ORB": "2.6", "DRB": "4.0", "TRB": "6.6", "AST": "6.2", "STL": "1.3", "BLK": "0.9", "TOV": "2.5", "PF": "3.3", "PTS": "23.5", "Awards": ""}{"Rk": "14", "Player": "Terry Cummings", "Age": "30", "Team": "SAS", "Pos": "PF", "G": "3", "GS": "3", "MP": "122", "FG": "10.0", "FGA": "19.5", "FG%": ".515", "3P": "0.0", "3PA": "0.3", "3P%": ".000", "2P": "10.0", "2PA": "19.2", "2P%": ".523", "eFG%": ".515", "FT": "3.0", "FTA": "5.9", "FT%": ".500", "ORB": "4.4", "DRB": "5.6", "TRB": "10.0", "AST": "2.1", "STL": "1.2", "BLK": "1.2", "TOV": "2.1", "PF": "2.7", "PTS": "23.0", "Awards": ""}{"Rk": "15", "Player": "\u0160ar\u016bnas Mar\u010diulionis", "Age": "27", "Team": "GSW", "Pos": "SG", "G": "4", "GS": "0", "MP": "133", "FG": "6.8", "FGA": "12.7", "FG%": ".532", "3P": "0.3", "3PA": "0.5", "3P%": ".500", "2P": "6.5", "2PA": "12.2", "2P%": ".533", "eFG%": ".543", "FT": "9.2", "FTA": "11.1", "FT%": ".829", "ORB": "0.8", "DRB": "1.6", "TRB": "2.4", "AST": "5.4", "STL": "0.8", "BLK": "0.3", "TOV": "1.1", "PF": "4.1", "PTS": "23.0", "Awards": ""}{"Rk": "16", "Player": "Mario Elie", "Age": "28", "Team": "GSW", "Pos": "SG", "G": "4", "GS": "2", "MP": "80", "FG": "10.4", "FGA": "16.2", "FG%": ".639", "3P": "0.9", "3PA": "0.9", "3P%": "1.000", "2P": "9.5", "2PA": "15.3", "2P%": ".618", "eFG%": ".667", "FT": "0.9", "FTA": "1.4", "FT%": ".667", "ORB": "5.0", "DRB": "5.0", "TRB": "9.9", "AST": "4.5", "STL": "2.3", "BLK": "0.0", "TOV": "2.7", "PF": "5.0", "PTS": "22.5", "Awards": ""}{"Rk": "17", "Player": "Reggie Miller", "Age": "26", "Team": "IND", "Pos": "SG", "G": "3", "GS": "3", "MP": "130", "FG": "6.9", "FGA": "11.9", "FG%": ".581", "3P": "1.9", "3PA": "3.0", "3P%": ".636", "2P": "5.0", "2PA": "8.9", "2P%": ".563", "eFG%": ".663", "FT": "6.6", "FTA": "8.3", "FT%": ".800", "ORB": "1.1", "DRB": "0.8", "TRB": "1.9", "AST": "3.9", "STL": "1.1", "BLK": "0.0", "TOV": "1.1", "PF": "3.3", "PTS": "22.4", "Awards": ""}{"Rk": "18", "Player": "Chris Gatling", "Age": "24", "Team": "GSW", "Pos": "PF", "G": "4", "GS": "0", "MP": "81", "FG": "8.0", "FGA": "12.9", "FG%": ".621", "3P": "0.0", "3PA": "0.0", "3P%": "", "2P": "8.0", "2PA": "12.9", "2P%": ".621", "eFG%": ".621", "FT": "6.2", "FTA": "9.8", "FT%": ".636", "ORB": "4.0", "DRB": "7.1", "TRB": "11.1", "AST": "0.0", "STL": "0.9", "BLK": "4.4", "TOV": "0.4", "PF": "6.2", "PTS": "22.2", "Awards": ""}{"Rk": "19", "Player": "Dra\u017een Petrovi\u0107", "Age": "27", "Team": "NJN", "Pos": "SG", "G": "4", "GS": "4", "MP": "163", "FG": "9.1", "FGA": "16.8", "FG%": ".539", "3P": "0.9", "3PA": "2.7", "3P%": ".333", "2P": "8.2", "2PA": "14.1", "2P%": ".578", "eFG%": ".566", "FT": "2.4", "FTA": "2.9", "FT%": ".846", "ORB": "0.9", "DRB": "1.3", "TRB": "2.2", "AST": "2.9", "STL": "0.9", "BLK": "0.2", "TOV": "1.8", "PF": "2.9", "PTS": "21.4", "Awards": ""}{"Rk": "20", "Player": "Danny Manning", "Age": "25", "Team": "LAC", "Pos": "PF", "G": "5", "GS": "5", "MP": "194", "FG": "8.5", "FGA": "15.0", "FG%": ".568", "3P": "0.2", "3PA": "0.6", "3P%": ".333", "2P": "8.4", "2PA": "14.5", "2P%": ".577", "eFG%": ".574", "FT": "3.7", "FTA": "5.8", "FT%": ".645", "ORB": "2.8", "DRB": "2.4", "TRB": "5.2", "AST": "2.6", "STL": "0.9", "BLK": "0.7", "TOV": "2.4", "PF": "3.9", "PTS": "21.0", "Awards": ""}{"Rk": "21", "Player": "Cedric Ceballos", "Age": "22", "Team": "PHO", "Pos": "SF", "G": "8", "GS": "8", "MP": "188", "FG": "8.4", "FGA": "15.3", "FG%": ".550", "3P": "0.0", "3PA": "0.0", "3P%": "", "2P": "8.4", "2PA": "15.3", "2P%": ".550", "eFG%": ".550", "FT": "3.8", "FTA": "5.7", "FT%": ".667", "ORB": "3.8", "DRB": "5.9", "TRB": "9.8", "AST": "2.3", "STL": "1.1", "BLK": "1.1", "TOV": "2.1", "PF": "2.7", "PTS": "20.7", "Awards": ""}{"Rk": "22", "Player": "Patrick Ewing", "Age": "29", "Team": "NYK", "Pos": "C", "G": "12", "GS": "12", "MP": "482", "FG": "8.1", "FGA": "17.9", "FG%": ".456", "3P": "0.0", "3PA": "0.1", "3P%": ".000", "2P": "8.1", "2PA": "17.8", "2P%": ".458", "eFG%": ".456", "FT": "4.0", "FTA": "5.5", "FT%": ".740", "ORB": "2.5", "DRB": "7.5", "TRB": "9.9", "AST": "2.0", "STL": "0.5", "BLK": "2.3", "TOV": "1.7", "PF": "3.7", "PTS": "20.3", "Awards": ""}{"Rk": "23", "Player": "Kevin Johnson", "Age": "25", "Team": "PHO", "Pos": "PG", "G": "8", "GS": "8", "MP": "335", "FG": "6.7", "FGA": "13.8", "FG%": ".484", "3P": "0.3", "3PA": "0.6", "3P%": ".500", "2P": "6.3", "2PA": "13.1", "2P%": ".484", "eFG%": ".496", "FT": "6.7", "FTA": "7.7", "FT%": ".861", "ORB": "0.9", "DRB": "2.7", "TRB": "3.5", "AST": "10.0", "STL": "1.3", "BLK": "0.2", "TOV": "2.7", "PF": "2.6", "PTS": "20.3", "Awards": ""}{"Rk": "24", "Player": "Tom Chambers", "Age": "32", "Team": "PHO", "Pos": "PF", "G": "7", "GS": "0", "MP": "194", "FG": "7.2", "FGA": "15.8", "FG%": ".459", "3P": "0.7", "3PA": "1.3", "3P%": ".571", "2P": "6.5", "2PA": "14.5", "2P%": ".449", "eFG%": ".482", "FT": "5.0", "FTA": "5.9", "FT%": ".844", "ORB": "1.5", "DRB": "4.3", "TRB": "5.8", "AST": "3.5", "STL": "0.4", "BLK": "0.9", "TOV": "2.8", "PF": "4.6", "PTS": "20.2", "Awards": ""}{"Rk": "25", "Player": "Ricky Pierce", "Age": "32", "Team": "SEA", "Pos": "SG", "G": "9", "GS": "9", "MP": "316", "FG": "7.2", "FGA": "14.9", "FG%": ".481", "3P": "0.3", "3PA": "1.3", "3P%": ".273", "2P": "6.8", "2PA": "13.7", "2P%": ".500", "eFG%": ".492", "FT": "5.4", "FTA": "6.2", "FT%": ".870", "ORB": "1.0", "DRB": "1.5", "TRB": "2.5", "AST": "3.2", "STL": "0.6", "BLK": "0.1", "TOV": "2.7", "PF": "2.7", "PTS": "20.1", "Awards": ""}{"Rk": "26", "Player": "Rafael Addison", "Age": "27", "Team": "NJN", "Pos": "SF", "G": "1", "GS": "0", "MP": "9", "FG": "8.0", "FGA": "28.0", "FG%": ".286", "3P": "4.0", "3PA": "8.0", "3P%": ".500", "2P": "4.0", "2PA": "20.0", "2P%": ".200", "eFG%": ".357", "FT": "0.0", "FTA": "0.0", "FT%": "", "ORB": "0.0", "DRB": "0.0", "TRB": "0.0", "AST": "4.0", "STL": "0.0", "BLK": "0.0", "TOV": "0.0", "PF": "0.0", "PTS": "20.0", "Awards": ""}{"Rk": "27", "Player": "Tim Hardaway", "Age": "25", "Team": "GSW", "Pos": "PG", "G": "4", "GS": "4", "MP": "176", "FG": "6.5", "FGA": "16.4", "FG%": ".400", "3P": "2.0", "3PA": "5.9", "3P%": ".345", "2P": "4.5", "2PA": "10.4", "2P%": ".431", "eFG%": ".463", "FT": "4.9", "FTA": "7.6", "FT%": ".649", "ORB": "1.2", "DRB": "1.8", "TRB": "3.1", "AST": "5.9", "STL": "2.7", "BLK": "0.0", "TOV": "2.9", "PF": "2.9", "PTS": "20.0", "Awards": ""}{"Rk": "28", "Player": "Chris Morris", "Age": "26", "Team": "NJN", "Pos": "SF", "G": "4", "GS": "4", "MP": "135", "FG": "8.5", "FGA": "15.5", "FG%": ".552", "3P": "1.1", "3PA": "2.7", "3P%": ".400", "2P": "7.5", "2PA": "12.8", "2P%": ".583", "eFG%": ".586", "FT": "1.9", "FTA": "2.4", "FT%": ".778", "ORB": "2.9", "DRB": "2.4", "TRB": "5.3", "AST": "1.3", "STL": "1.9", "BLK": "1.9", "TOV": "2.1", "PF": "2.9", "PTS": "20.0", "Awards": ""}{"Rk": "29", "Player": "Terry Teagle", "Age": "31", "Team": "LAL", "Pos": "SG", "G": "4", "GS": "2", "MP": "126", "FG": "7.7", "FGA": "15.7", "FG%": ".491", "3P": "0.0", "3PA": "0.0", "3P%": "", "2P": "7.7", "2PA": "15.7", "2P%": ".491", "eFG%": ".491", "FT": "4.6", "FTA": "5.7", "FT%": ".800", "ORB": "0.9", "DRB": "2.9", "TRB": "3.7", "AST": "2.3", "STL": "1.4", "BLK": "0.6", "TOV": "2.3", "PF": "5.1", "PTS": "20.0", "Awards": ""}{"Rk": "30", "Player": "Derrick Coleman", "Age": "24", "Team": "NJN", "Pos": "PF", "G": "4", "GS": "4", "MP": "162", "FG": "8.0", "FGA": "16.4", "FG%": ".486", "3P": "0.2", "3PA": "1.3", "3P%": ".167", "2P": "7.8", "2PA": "15.1", "2P%": ".515", "eFG%": ".493", "FT": "3.6", "FTA": "4.7", "FT%": ".762", "ORB": "2.9", "DRB": "7.1", "TRB": "10.0", "AST": "4.7", "STL": "1.6", "BLK": "0.9", "TOV": "2.4", "PF": "2.7", "PTS": "19.8", "Awards": ""}{"Rk": "31", "Player": "Kennard Winchester", "Age": "25", "Team": "NYK", "Pos": "SF", "G": "3", "GS": "0", "MP": "11", "FG": "9.8", "FGA": "16.4", "FG%": ".600", "3P": "0.0", "3PA": "0.0", "3P%": "", "2P": "9.8", "2PA": "16.4", "2P%": ".600", "eFG%": ".600", "FT": "0.0", "FTA": "3.3", "FT%": ".000", "ORB": "0.0", "DRB": "0.0", "TRB": "0.0", "AST": "6.5", "STL": "0.0", "BLK": "0.0", "TOV": "3.3", "PF": "0.0", "PTS": "19.6", "Awards": ""}{"Rk": "32", "Player": "Dana Barros", "Age": "24", "Team": "SEA", "Pos": "PG", "G": "7", "GS": "0", "MP": "96", "FG": "7.9", "FGA": "15.0", "FG%": ".525", "3P": "3.7", "3PA": "6.4", "3P%": ".588", "2P": "4.1", "2PA": "8.6", "2P%": ".478", "eFG%": ".650", "FT": "0.0", "FTA": "0.0", "FT%": "", "ORB": "0.4", "DRB": "2.3", "TRB": "2.6", "AST": "3.0", "STL": "1.5", "BLK": "0.0", "TOV": "2.3", "PF": "4.1", "PTS": "19.5", "Awards": ""}{"Rk": "33", "Player": "Antoine Carr", "Age": "30", "Team": "SAS", "Pos": "PF", "G": "3", "GS": "3", "MP": "109", "FG": "7.9", "FGA": "14.5", "FG%": ".545", "3P": "0.3", "3PA": "0.7", "3P%": ".500", "2P": "7.6", "2PA": "13.9", "2P%": ".548", "eFG%": ".557", "FT": "3.3", "FTA": "5.3", "FT%": ".625", "ORB": "2.6", "DRB": "5.0", "TRB": "7.6", "AST": "1.0", "STL": "0.7", "BLK": "3.6", "TOV": "1.3", "PF": "4.6", "PTS": "19.5", "Awards": ""}{"Rk": "34", "Player": "Jeff Malone", "Age": "30", "Team": "UTA", "Pos": "SG", "G": "16", "GS": "16", "MP": "610", "FG": "7.9", "FGA": "16.2", "FG%": ".487", "3P": "0.1", "3PA": "0.2", "3P%": ".333", "2P": "7.8", "2PA": "16.1", "2P%": ".489", "eFG%": ".489", "FT": "3.7", "FTA": "4.2", "FT%": ".861", "ORB": "0.7", "DRB": "1.6", "TRB": "2.3", "AST": "1.8", "STL": "0.5", "BLK": "0.1", "TOV": "1.5", "PF": "1.9", "PTS": "19.5", "Awards": ""}{"Rk": "35", "Player": "Mark Price", "Age": "27", "Team": "CLE", "Pos": "PG", "G": "17", "GS": "17", "MP": "603", "FG": "7.0", "FGA": "14.2", "FG%": ".496", "3P": "1.5", "3PA": "4.1", "3P%": ".362", "2P": "5.6", "2PA": "10.1", "2P%": ".550", "eFG%": ".548", "FT": "3.9", "FTA": "4.4", "FT%": ".904", "ORB": "0.6", "DRB": "1.9", "TRB": "2.5", "AST": "7.6", "STL": "1.4", "BLK": "0.2", "TOV": "3.3", "PF": "2.0", "PTS": "19.5", "Awards": ""}{"Rk": "36", "Player": "Kevin McHale", "Age": "34", "Team": "BOS", "Pos": "PF", "G": "10", "GS": "0", "MP": "306", "FG": "7.6", "FGA": "14.8", "FG%": ".516", "3P": "0.0", "3PA": "0.1", "3P%": ".000", "2P": "7.6", "2PA": "14.7", "2P%": ".520", "eFG%": ".516", "FT": "4.1", "FTA": "5.2", "FT%": ".795", "ORB": "2.5", "DRB": "5.4", "TRB": "7.9", "AST": "1.5", "STL": "0.6", "BLK": "0.6", "TOV": "1.1", "PF": "4.0", "PTS": "19.4", "Awards": ""}{"Rk": "37", "Player": "Tim Perry", "Age": "26", "Team": "PHO", "Pos": "PF", "G": "8", "GS": "8", "MP": "185", "FG": "7.4", "FGA": "12.3", "FG%": ".603", "3P": "0.0", "3PA": "0.0", "3P%": "", "2P": "7.4", "2PA": "12.3", "2P%": ".603", "eFG%": ".603", "FT": "4.5", "FTA": "6.2", "FT%": ".719", "ORB": "2.3", "DRB": "5.3", "TRB": "7.6", "AST": "2.1", "STL": "0.6", "BLK": "1.2", "TOV": "2.7", "PF": "4.7", "PTS": "19.3", "Awards": ""}{"Rk": "38", "Player": "Brad Daugherty", "Age": "26", "Team": "CLE", "Pos": "C", "G": "17", "GS": "17", "MP": "687", "FG": "6.5", "FGA": "12.3", "FG%": ".528", "3P": "0.0", "3PA": "0.1", "3P%": ".000", "2P": "6.5", "2PA": "12.3", "2P%": ".530", "eFG%": ".528", "FT": "6.2", "FTA": "7.6", "FT%": ".814", "ORB": "1.9", "DRB": "7.2", "TRB": "9.1", "AST": "3.0", "STL": "0.6", "BLK": "0.9", "TOV": "1.9", "PF": "2.5", "PTS": "19.2", "Awards": ""}{"Rk": "39", "Player": "Rony Seikaly", "Age": "26", "Team": "MIA", "Pos": "C", "G": "3", "GS": "3", "MP": "117", "FG": "5.8", "FGA": "10.8", "FG%": ".543", "3P": "0.0", "3PA": "0.0", "3P%": "", "2P": "5.8", "2PA": "10.8", "2P%": ".543", "eFG%": ".543", "FT": "7.4", "FTA": "9.8", "FT%": ".750", "ORB": "3.4", "DRB": "5.8", "TRB": "9.2", "AST": "1.2", "STL": "0.3", "BLK": "1.5", "TOV": "2.8", "PF": "4.6", "PTS": "19.1", "Awards": ""}{"Rk": "40", "Player": "Detlef Schrempf", "Age": "29", "Team": "IND", "Pos": "PF", "G": "3", "GS": "0", "MP": "120", "FG": "5.4", "FGA": "14.1", "FG%": ".383", "3P": "0.6", "3PA": "1.2", "3P%": ".500", "2P": "4.8", "2PA": "12.9", "2P%": ".372", "eFG%": ".404", "FT": "7.5", "FTA": "8.4", "FT%": ".893", "ORB": "3.6", "DRB": "8.1", "TRB": "11.7", "AST": "2.1", "STL": "0.6", "BLK": "0.3", "TOV": "2.1", "PF": "3.0", "PTS": "18.9", "Awards": ""}{"Rk": "41", "Player": "Terry Porter", "Age": "28", "Team": "POR", "Pos": "PG", "G": "21", "GS": "21", "MP": "870", "FG": "6.1", "FGA": "11.8", "FG%": ".516", "3P": "1.5", "3PA": "3.2", "3P%": ".474", "2P": "4.6", "2PA": "8.6", "2P%": ".531", "eFG%": ".581", "FT": "4.9", "FTA": "5.9", "FT%": ".832", "ORB": "1.0", "DRB": "3.0", "TRB": "4.0", "AST": "5.8", "STL": "0.9", "BLK": "0.1", "TOV": "1.9", "PF": "2.0", "PTS": "18.6", "Awards": ""}{"Rk": "42", "Player": "Bimbo Coles", "Age": "23", "Team": "MIA", "Pos": "PG", "G": "3", "GS": "0", "MP": "45", "FG": "5.6", "FGA": "8.0", "FG%": ".700", "3P": "0.8", "3PA": "0.8", "3P%": "1.000", "2P": "4.8", "2PA": "7.2", "2P%": ".667", "eFG%": ".750", "FT": "6.4", "FTA": "8.0", "FT%": ".800", "ORB": "1.6", "DRB": "4.0", "TRB": "5.6", "AST": "4.8", "STL": "2.4", "BLK": "0.0", "TOV": "4.0", "PF": "4.0", "PTS": "18.4", "Awards": ""}{"Rk": "43", "Player": "Byron Scott", "Age": "30", "Team": "LAL", "Pos": "SG", "G": "4", "GS": "4", "MP": "148", "FG": "5.4", "FGA": "10.7", "FG%": ".500", "3P": "1.7", "3PA": "2.9", "3P%": ".583", "2P": "3.6", "2PA": "7.8", "2P%": ".469", "eFG%": ".580", "FT": "5.8", "FTA": "6.6", "FT%": ".889", "ORB": "0.7", "DRB": "1.7", "TRB": "2.4", "AST": "3.4", "STL": "1.5", "BLK": "0.2", "TOV": "1.2", "PF": "2.4", "PTS": "18.2", "Awards": ""}{"Rk": "44", "Player": "Danny Ainge", "Age": "32", "Team": "POR", "Pos": "SG", "G": "21", "GS": "0", "MP": "449", "FG": "6.5", "FGA": "13.6", "FG%": ".479", "3P": "1.7", "3PA": "4.2", "3P%": ".404", "2P": "4.8", "2PA": "9.4", "2P%": ".513", "eFG%": ".541", "FT": "3.1", "FTA": "3.8", "FT%": ".830", "ORB": "0.6", "DRB": "2.6", "TRB": "3.2", "AST": "3.9", "STL": "1.2", "BLK": "0.1", "TOV": "2.0", "PF": "4.7", "PTS": "17.8", "Awards": ""}{"Rk": "45", "Player": "Xavier McDaniel", "Age": "28", "Team": "NYK", "Pos": "SF", "G": "12", "GS": "12", "MP": "458", "FG": "7.4", "FGA": "15.5", "FG%": ".477", "3P": "0.2", "3PA": "0.6", "3P%": ".250", "2P": "7.2", "2PA": "14.9", "2P%": ".487", "eFG%": ".482", "FT": "2.8", "FTA": "3.9", "FT%": ".735", "ORB": "3.4", "DRB": "3.4", "TRB": "6.8", "AST": "1.8", "STL": "0.7", "BLK": "0.2", "TOV": "2.1", "PF": "2.7", "PTS": "17.8", "Awards": ""}{"Rk": "46", "Player": "Billy Owens", "Age": "22", "Team": "GSW", "Pos": "PF", "G": "4", "GS": "4", "MP": "157", "FG": "6.9", "FGA": "13.1", "FG%": ".526", "3P": "0.0", "3PA": "0.0", "3P%": "", "2P": "6.9", "2PA": "13.1", "2P%": ".526", "eFG%": ".526", "FT": "3.9", "FTA": "6.2", "FT%": ".630", "ORB": "3.0", "DRB": "4.6", "TRB": "7.6", "AST": "3.0", "STL": "1.8", "BLK": "0.5", "TOV": "1.4", "PF": "3.2", "PTS": "17.7", "Awards": ""}{"Rk": "47", "Player": "John Starks", "Age": "26", "Team": "NYK", "Pos": "SG", "G": "12", "GS": "0", "MP": "295", "FG": "5.6", "FGA": "15.0", "FG%": ".374", "3P": "1.3", "3PA": "5.6", "3P%": ".239", "2P": "4.3", "2PA": "9.4", "2P%": ".455", "eFG%": ".419", "FT": "5.1", "FTA": "6.3", "FT%": ".808", "ORB": "0.9", "DRB": "2.8", "TRB": "3.7", "AST": "4.6", "STL": "2.1", "BLK": "0.0", "TOV": "2.7", "PF": "5.5", "PTS": "17.7", "Awards": ""}{"Rk": "48", "Player": "Dan Majerle", "Age": "26", "Team": "PHO", "Pos": "SF", "G": "7", "GS": "0", "MP": "266", "FG": "6.5", "FGA": "15.0", "FG%": ".432", "3P": "1.2", "3PA": "4.5", "3P%": ".273", "2P": "5.3", "2PA": "10.6", "2P%": ".500", "eFG%": ".473", "FT": "3.4", "FTA": "3.5", "FT%": ".962", "ORB": "1.8", "DRB": "4.2", "TRB": "6.0", "AST": "2.7", "STL": "1.4", "BLK": "0.0", "TOV": "1.2", "PF": "1.5", "PTS": "17.6", "Awards": ""}{"Rk": "49", "Player": "Alaa Abdelnaby", "Age": "23", "Team": "POR", "Pos": "PF", "G": "8", "GS": "0", "MP": "25", "FG": "7.2", "FGA": "14.4", "FG%": ".500", "3P": "0.0", "3PA": "0.0", "3P%": "", "2P": "7.2", "2PA": "14.4", "2P%": ".500", "eFG%": ".500", "FT": "2.9", "FTA": "5.8", "FT%": ".500", "ORB": "0.0", "DRB": "5.8", "TRB": "5.8", "AST": "2.9", "STL": "0.0", "BLK": "0.0", "TOV": "2.9", "PF": "5.8", "PTS": "17.3", "Awards": ""}{"Rk": "50", "Player": "Steve Burtt", "Age": "29", "Team": "PHO", "Pos": "SG", "G": "8", "GS": "0", "MP": "104", "FG": "5.5", "FGA": "13.2", "FG%": ".421", "3P": "0.0", "3PA": "0.7", "3P%": ".000", "2P": "5.5", "2PA": "12.5", "2P%": ".444", "eFG%": ".421", "FT": "6.2", "FTA": "7.3", "FT%": ".857", "ORB": "1.0", "DRB": "3.1", "TRB": "4.2", "AST": "4.8", "STL": "1.7", "BLK": "0.0", "TOV": "2.8", "PF": "6.2", "PTS": "17.3", "Awards": ""}{"Rk": "51", "Player": "Steve Smith", "Age": "22", "Team": "MIA", "Pos": "SG", "G": "3", "GS": "3", "MP": "100", "FG": "6.5", "FGA": "12.2", "FG%": ".529", "3P": "2.5", "3PA": "4.0", "3P%": ".636", "2P": "4.0", "2PA": "8.3", "2P%": ".478", "eFG%": ".632", "FT": "1.8", "FTA": "2.2", "FT%": ".833", "ORB": "1.1", "DRB": "1.1", "TRB": "2.2", "AST": "5.4", "STL": "1.4", "BLK": "0.4", "TOV": "1.1", "PF": "0.7", "PTS": "17.3", "Awards": ""}{"Rk": "52", "Player": "Kiki Vandeweghe", "Age": "33", "Team": "NYK", "Pos": "SF", "G": "8", "GS": "0", "MP": "75", "FG": "6.2", "FGA": "11.5", "FG%": ".542", "3P": "1.9", "3PA": "2.4", "3P%": ".800", "2P": "4.3", "2PA": "9.1", "2P%": ".474", "eFG%": ".625", "FT": "2.9", "FTA": "3.4", "FT%": ".857", "ORB": "1.4", "DRB": "1.4", "TRB": "2.9", "AST": "1.9", "STL": "1.0", "BLK": "0.5", "TOV": "0.5", "PF": "4.8", "PTS": "17.3", "Awards": ""}{"Rk": "53", "Player": "Stacey King", "Age": "25", "Team": "CHI", "Pos": "PF", "G": "14", "GS": "0", "MP": "111", "FG": "5.8", "FGA": "13.0", "FG%": ".450", "3P": "0.6", "3PA": "0.6", "3P%": "1.000", "2P": "5.2", "2PA": "12.3", "2P%": ".421", "eFG%": ".475", "FT": "4.9", "FTA": "7.5", "FT%": ".652", "ORB": "2.3", "DRB": "4.2", "TRB": "6.5", "AST": "1.6", "STL": "1.6", "BLK": "0.6", "TOV": "3.2", "PF": "3.9", "PTS": "17.2", "Awards": ""}{"Rk": "54", "Player": "Glen Rice", "Age": "24", "Team": "MIA", "Pos": "SF", "G": "3", "GS": "3", "MP": "119", "FG": "7.3", "FGA": "19.4", "FG%": ".375", "3P": "0.9", "3PA": "3.6", "3P%": ".250", "2P": "6.4", "2PA": "15.7", "2P%": ".404", "eFG%": ".398", "FT": "1.8", "FTA": "2.1", "FT%": ".857", "ORB": "0.9", "DRB": "2.1", "TRB": "3.0", "AST": "1.5", "STL": "0.6", "BLK": "0.0", "TOV": "1.8", "PF": "2.1", "PTS": "17.2", "Awards": ""}{"Rk": "55", "Player": "Jeff Hornacek", "Age": "28", "Team": "PHO", "Pos": "SG", "G": "8", "GS": "8", "MP": "343", "FG": "6.5", "FGA": "13.4", "FG%": ".484", "3P": "0.8", "3PA": "1.8", "3P%": ".471", "2P": "5.7", "2PA": "11.7", "2P%": ".486", "eFG%": ".516", "FT": "3.3", "FTA": "3.6", "FT%": ".912", "ORB": "1.3", "DRB": "4.1", "TRB": "5.4", "AST": "4.4", "STL": "1.5", "BLK": "0.2", "TOV": "2.0", "PF": "2.4", "PTS": "17.1", "Awards": ""}{"Rk": "56", "Player": "Scottie Pippen", "Age": "26", "Team": "CHI", "Pos": "SF", "G": "22", "GS": "22", "MP": "899", "FG": "6.1", "FGA": "13.0", "FG%": ".468", "3P": "0.2", "3PA": "1.0", "3P%": ".250", "2P": "5.8", "2PA": "12.1", "2P%": ".485", "eFG%": ".477", "FT": "4.7", "FTA": "6.2", "FT%": ".761", "ORB": "2.4", "DRB": "5.4", "TRB": "7.7", "AST": "5.9", "STL": "1.6", "BLK": "1.0", "TOV": "2.8", "PF": "2.9", "PTS": "17.1", "Awards": ""}{"Rk": "57", "Player": "Loy Vaught", "Age": "23", "Team": "LAC", "Pos": "PF", "G": "5", "GS": "0", "MP": "36", "FG": "7.0", "FGA": "11.0", "FG%": ".636", "3P": "1.0", "3PA": "1.0", "3P%": "1.000", "2P": "6.0", "2PA": "10.0", "2P%": ".600", "eFG%": ".682", "FT": "2.0", "FTA": "2.0", "FT%": "1.000", "ORB": "2.0", "DRB": "10.0", "TRB": "12.0", "AST": "4.0", "STL": "1.0", "BLK": "1.0", "TOV": "1.0", "PF": "3.0", "PTS": "17.0", "Awards": ""}{"Rk": "58", "Player": "Micheal Williams", "Age": "25", "Team": "IND", "Pos": "PG", "G": "3", "GS": "3", "MP": "106", "FG": "6.1", "FGA": "14.6", "FG%": ".419", "3P": "1.0", "3PA": "3.1", "3P%": ".333", "2P": "5.1", "2PA": "11.5", "2P%": ".441", "eFG%": ".453", "FT": "3.7", "FTA": "5.1", "FT%": ".733", "ORB": "0.3", "DRB": "2.4", "TRB": "2.7", "AST": "8.2", "STL": "3.1", "BLK": "0.0", "TOV": "2.4", "PF": "4.1", "PTS": "17.0", "Awards": ""}{"Rk": "59", "Player": "Derrick McKey", "Age": "25", "Team": "SEA", "Pos": "SF", "G": "9", "GS": "9", "MP": "315", "FG": "5.9", "FGA": "11.3", "FG%": ".525", "3P": "0.6", "3PA": "1.8", "3P%": ".313", "2P": "5.4", "2PA": "9.5", "2P%": ".566", "eFG%": ".551", "FT": "4.3", "FTA": "5.1", "FT%": ".844", "ORB": "1.9", "DRB": "3.1", "TRB": "5.0", "AST": "2.7", "STL": "0.8", "BLK": "1.4", "TOV": "2.5", "PF": "4.2", "PTS": "16.8", "Awards": ""}{"Rk": "60", "Player": "Greg Sutton", "Age": "24", "Team": "SAS", "Pos": "PG", "G": "2", "GS": "0", "MP": "15", "FG": "4.8", "FGA": "14.4", "FG%": ".333", "3P": "0.0", "3PA": "4.8", "3P%": ".000", "2P": "4.8", "2PA": "9.6", "2P%": ".500", "eFG%": ".333", "FT": "7.2", "FTA": "7.2", "FT%": "1.000", "ORB": "0.0", "DRB": "0.0", "TRB": "0.0", "AST": "4.8", "STL": "2.4", "BLK": "2.4", "TOV": "0.0", "PF": "7.2", "PTS": "16.8", "Awards": ""}{"Rk": "61", "Player": "Shawn Kemp", "Age": "22", "Team": "SEA", "Pos": "PF", "G": "9", "GS": "9", "MP": "338", "FG": "5.1", "FGA": "10.8", "FG%": ".475", "3P": "0.0", "3PA": "0.0", "3P%": "", "2P": "5.1", "2PA": "10.8", "2P%": ".475", "eFG%": ".475", "FT": "6.5", "FTA": "8.5", "FT%": ".763", "ORB": "5.0", "DRB": "6.7", "TRB": "11.7", "AST": "0.4", "STL": "0.5", "BLK": "1.5", "TOV": "2.9", "PF": "4.4", "PTS": "16.7", "Awards": ""}{"Rk": "62", "Player": "Bob McCann", "Age": "27", "Team": "DET", "Pos": "SF", "G": "1", "GS": "0", "MP": "13", "FG": "8.3", "FGA": "16.6", "FG%": ".500", "3P": "0.0", "3PA": "0.0", "3P%": "", "2P": "8.3", "2PA": "16.6", "2P%": ".500", "eFG%": ".500", "FT": "0.0", "FTA": "0.0", "FT%": "", "ORB": "2.8", "DRB": "2.8", "TRB": "5.5", "AST": "0.0", "STL": "0.0", "BLK": "2.8", "TOV": "5.5", "PF": "5.5", "PTS": "16.6", "Awards": ""}{"Rk": "63", "Player": "Brad Sellers", "Age": "29", "Team": "DET", "Pos": "PF", "G": "2", "GS": "0", "MP": "13", "FG": "5.5", "FGA": "11.1", "FG%": ".500", "3P": "0.0", "3PA": "0.0", "3P%": "", "2P": "5.5", "2PA": "11.1", "2P%": ".500", "eFG%": ".500", "FT": "5.5", "FTA": "5.5", "FT%": "1.000", "ORB": "0.0", "DRB": "0.0", "TRB": "0.0", "AST": "5.5", "STL": "0.0", "BLK": "5.5", "TOV": "0.0", "PF": "0.0", "PTS": "16.6", "Awards": ""}{"Rk": "64", "Player": "Cliff Robinson", "Age": "31", "Team": "LAL", "Pos": "PF", "G": "3", "GS": "0", "MP": "24", "FG": "4.5", "FGA": "15.0", "FG%": ".300", "3P": "0.0", "3PA": "0.0", "3P%": "", "2P": "4.5", "2PA": "15.0", "2P%": ".300", "eFG%": ".300", "FT": "7.5", "FTA": "12.0", "FT%": ".625", "ORB": "3.0", "DRB": "6.0", "TRB": "9.0", "AST": "1.5", "STL": "4.5", "BLK": "1.5", "TOV": "3.0", "PF": "9.0", "PTS": "16.5", "Awards": ""}{"Rk": "65", "Player": "Jerome Kersey", "Age": "29", "Team": "POR", "Pos": "SF", "G": "21", "GS": "21", "MP": "756", "FG": "6.2", "FGA": "12.2", "FG%": ".510", "3P": "0.0", "3PA": "0.1", "3P%": ".000", "2P": "6.2", "2PA": "12.1", "2P%": ".516", "eFG%": ".510", "FT": "3.8", "FTA": "5.4", "FT%": ".693", "ORB": "2.8", "DRB": "4.9", "TRB": "7.7", "AST": "3.6", "STL": "2.0", "BLK": "0.9", "TOV": "2.5", "PF": "4.0", "PTS": "16.2", "Awards": ""}{"Rk": "66", "Player": "Larry Nance", "Age": "32", "Team": "CLE", "Pos": "PF", "G": "17", "GS": "17", "MP": "681", "FG": "6.6", "FGA": "13.3", "FG%": ".494", "3P": "0.0", "3PA": "0.1", "3P%": ".000", "2P": "6.6", "2PA": "13.2", "2P%": ".496", "eFG%": ".494", "FT": "3.1", "FTA": "3.7", "FT%": ".829", "ORB": "2.4", "DRB": "5.9", "TRB": "8.3", "AST": "2.3", "STL": "0.7", "BLK": "2.4", "TOV": "1.4", "PF": "3.0", "PTS": "16.2", "Awards": ""}{"Rk": "67", "Player": "Hot Rod Williams", "Age": "29", "Team": "CLE", "Pos": "C", "G": "17", "GS": "0", "MP": "567", "FG": "5.3", "FGA": "9.8", "FG%": ".545", "3P": "0.0", "3PA": "0.0", "3P%": "", "2P": "5.3", "2PA": "9.8", "2P%": ".545", "eFG%": ".545", "FT": "5.5", "FTA": "6.9", "FT%": ".798", "ORB": "3.2", "DRB": "5.1", "TRB": "8.3", "AST": "2.7", "STL": "1.5", "BLK": "1.1", "TOV": "2.0", "PF": "3.7", "PTS": "16.2", "Awards": ""}{"Rk": "68", "Player": "John Battle", "Age": "29", "Team": "CLE", "Pos": "SG", "G": "15", "GS": "0", "MP": "202", "FG": "6.1", "FGA": "14.6", "FG%": ".415", "3P": "0.0", "3PA": "0.4", "3P%": ".000", "2P": "6.1", "2PA": "14.3", "2P%": ".425", "eFG%": ".415", "FT": "3.7", "FTA": "4.1", "FT%": ".913", "ORB": "0.7", "DRB": "1.4", "TRB": "2.1", "AST": "2.7", "STL": "0.9", "BLK": "0.2", "TOV": "3.2", "PF": "2.0", "PTS": "15.9", "Awards": ""}{"Rk": "69", "Player": "Ron Harper", "Age": "28", "Team": "LAC", "Pos": "SG", "G": "5", "GS": "5", "MP": "206", "FG": "6.8", "FGA": "15.2", "FG%": ".448", "3P": "0.2", "3PA": "1.6", "3P%": ".111", "2P": "6.6", "2PA": "13.6", "2P%": ".487", "eFG%": ".454", "FT": "1.9", "FTA": "2.4", "FT%": ".786", "ORB": "1.7", "DRB": "3.8", "TRB": "5.6", "AST": "4.0", "STL": "0.9", "BLK": "0.7", "TOV": "2.6", "PF": "2.3", "PTS": "15.7", "Awards": ""}{"Rk": "70", "Player": "Clifford Robinson", "Age": "25", "Team": "POR", "Pos": "SF", "G": "21", "GS": "0", "MP": "522", "FG": "6.3", "FGA": "13.6", "FG%": ".462", "3P": "0.1", "3PA": "0.4", "3P%": ".167", "2P": "6.2", "2PA": "13.2", "2P%": ".471", "eFG%": ".464", "FT": "3.0", "FTA": "5.3", "FT%": ".571", "ORB": "1.7", "DRB": "4.3", "TRB": "6.1", "AST": "3.0", "STL": "1.5", "BLK": "1.4", "TOV": "1.9", "PF": "5.8", "PTS": "15.7", "Awards": ""}{"Rk": "71", "Player": "Rick Fox", "Age": "22", "Team": "BOS", "Pos": "SF", "G": "8", "GS": "0", "MP": "67", "FG": "5.9", "FGA": "12.4", "FG%": ".478", "3P": "1.6", "3PA": "3.2", "3P%": ".500", "2P": "4.3", "2PA": "9.1", "2P%": ".471", "eFG%": ".543", "FT": "2.1", "FTA": "2.1", "FT%": "1.000", "ORB": "1.6", "DRB": "1.6", "TRB": "3.2", "AST": "2.1", "STL": "1.1", "BLK": "1.1", "TOV": "1.1", "PF": "5.9", "PTS": "15.6", "Awards": ""}{"Rk": "72", "Player": "George McCloud", "Age": "24", "Team": "IND", "Pos": "SF", "G": "2", "GS": "2", "MP": "53", "FG": "4.1", "FGA": "8.2", "FG%": ".500", "3P": "2.0", "3PA": "4.1", "3P%": ".500", "2P": "2.0", "2PA": "4.1", "2P%": ".500", "eFG%": ".625", "FT": "5.4", "FTA": "7.5", "FT%": ".727", "ORB": "0.0", "DRB": "1.4", "TRB": "1.4", "AST": "4.1", "STL": "1.4", "BLK": "0.7", "TOV": "2.0", "PF": "3.4", "PTS": "15.6", "Awards": ""}{"Rk": "73", "Player": "Chuck Person", "Age": "27", "Team": "IND", "Pos": "SF", "G": "3", "GS": "3", "MP": "118", "FG": "5.8", "FGA": "14.3", "FG%": ".404", "3P": "1.5", "3PA": "4.6", "3P%": ".333", "2P": "4.3", "2PA": "9.8", "2P%": ".438", "eFG%": ".457", "FT": "2.4", "FTA": "3.7", "FT%": ".667", "ORB": "0.3", "DRB": "2.4", "TRB": "2.7", "AST": "2.1", "STL": "0.6", "BLK": "0.0", "TOV": "1.8", "PF": "3.4", "PTS": "15.6", "Awards": ""}{"Rk": "74", "Player": "Chucky Brown", "Age": "23", "Team": "LAL", "Pos": "SF", "G": "3", "GS": "0", "MP": "44", "FG": "6.5", "FGA": "15.5", "FG%": ".421", "3P": "0.0", "3PA": "0.8", "3P%": ".000", "2P": "6.5", "2PA": "14.7", "2P%": ".444", "eFG%": ".421", "FT": "2.5", "FTA": "4.9", "FT%": ".500", "ORB": "2.5", "DRB": "6.5", "TRB": "9.0", "AST": "1.6", "STL": "0.0", "BLK": "1.6", "TOV": "0.8", "PF": "2.5", "PTS": "15.5", "Awards": ""}{"Rk": "75", "Player": "Sean Elliott", "Age": "23", "Team": "SAS", "Pos": "SF", "G": "3", "GS": "3", "MP": "137", "FG": "5.0", "FGA": "10.5", "FG%": ".475", "3P": "1.3", "3PA": "2.1", "3P%": ".625", "2P": "3.7", "2PA": "8.4", "2P%": ".438", "eFG%": ".538", "FT": "4.2", "FTA": "4.7", "FT%": ".889", "ORB": "1.1", "DRB": "2.4", "TRB": "3.4", "AST": "2.1", "STL": "0.8", "BLK": "1.1", "TOV": "1.6", "PF": "1.6", "PTS": "15.5", "Awards": ""}{"Rk": "76", "Player": "Orlando Woolridge", "Age": "32", "Team": "DET", "Pos": "SF", "G": "5", "GS": "5", "MP": "128", "FG": "6.5", "FGA": "14.6", "FG%": ".442", "3P": "0.0", "3PA": "0.0", "3P%": "", "2P": "6.5", "2PA": "14.6", "2P%": ".442", "eFG%": ".442", "FT": "2.5", "FTA": "4.5", "FT%": ".563", "ORB": "1.4", "DRB": "1.4", "TRB": "2.8", "AST": "0.8", "STL": "0.3", "BLK": "0.3", "TOV": "1.7", "PF": "3.9", "PTS": "15.5", "Awards": ""}{"Rk": "77", "Player": "Chris Mullin", "Age": "28", "Team": "GSW", "Pos": "SF", "G": "4", "GS": "4", "MP": "168", "FG": "5.8", "FGA": "13.5", "FG%": ".429", "3P": "0.9", "3PA": "2.6", "3P%": ".333", "2P": "4.9", "2PA": "10.9", "2P%": ".451", "eFG%": ".460", "FT": "2.8", "FTA": "3.0", "FT%": ".929", "ORB": "0.6", "DRB": "1.9", "TRB": "2.6", "AST": "2.6", "STL": "1.1", "BLK": "0.4", "TOV": "1.7", "PF": "1.7", "PTS": "15.2", "Awards": ""}{"Rk": "78", "Player": "John Salley", "Age": "27", "Team": "DET", "Pos": "PF", "G": "5", "GS": "1", "MP": "149", "FG": "4.8", "FGA": "10.6", "FG%": ".455", "3P": "0.0", "3PA": "0.2", "3P%": ".000", "2P": "4.8", "2PA": "10.4", "2P%": ".465", "eFG%": ".455", "FT": "5.6", "FTA": "6.8", "FT%": ".821", "ORB": "2.4", "DRB": "4.8", "TRB": "7.2", "AST": "3.4", "STL": "0.7", "BLK": "3.4", "TOV": "2.2", "PF": "4.3", "PTS": "15.2", "Awards": ""}{"Rk": "79", "Player": "Brian Shaw", "Age": "25", "Team": "MIA", "Pos": "PG", "G": "3", "GS": "3", "MP": "85", "FG": "5.9", "FGA": "12.7", "FG%": ".467", "3P": "1.3", "3PA": "2.1", "3P%": ".600", "2P": "4.7", "2PA": "10.6", "2P%": ".440", "eFG%": ".517", "FT": "2.1", "FTA": "3.4", "FT%": ".625", "ORB": "0.8", "DRB": "4.7", "TRB": "5.5", "AST": "5.1", "STL": "0.8", "BLK": "0.0", "TOV": "3.0", "PF": "5.5", "PTS": "15.2", "Awards": ""}{"Rk": "80", "Player": "Larry Bird", "Age": "35", "Team": "BOS", "Pos": "SF", "G": "4", "GS": "2", "MP": "107", "FG": "7.1", "FGA": "14.1", "FG%": ".500", "3P": "0.0", "3PA": "1.7", "3P%": ".000", "2P": "7.1", "2PA": "12.4", "2P%": ".568", "eFG%": ".500", "FT": "1.0", "FTA": "1.3", "FT%": ".750", "ORB": "0.7", "DRB": "5.4", "TRB": "6.1", "AST": "7.1", "STL": "0.3", "BLK": "0.7", "TOV": "2.0", "PF": "2.4", "PTS": "15.1", "Awards": ""}{"Rk": "81", "Player": "Vern Fleming", "Age": "29", "Team": "IND", "Pos": "PG", "G": "3", "GS": "0", "MP": "51", "FG": "7.1", "FGA": "12.7", "FG%": ".556", "3P": "0.0", "3PA": "0.0", "3P%": "", "2P": "7.1", "2PA": "12.7", "2P%": ".556", "eFG%": ".556", "FT": "0.7", "FTA": "2.1", "FT%": ".333", "ORB": "0.0", "DRB": "1.4", "TRB": "1.4", "AST": "4.2", "STL": "2.1", "BLK": "0.0", "TOV": "2.8", "PF": "3.5", "PTS": "14.8", "Awards": ""}{"Rk": "82", "Player": "Tony Brown", "Age": "31", "Team": "SEA", "Pos": "SF", "G": "5", "GS": "0", "MP": "22", "FG": "3.3", "FGA": "9.8", "FG%": ".333", "3P": "1.6", "3PA": "6.5", "3P%": ".250", "2P": "1.6", "2PA": "3.3", "2P%": ".500", "eFG%": ".417", "FT": "6.5", "FTA": "11.5", "FT%": ".571", "ORB": "0.0", "DRB": "3.3", "TRB": "3.3", "AST": "3.3", "STL": "0.0", "BLK": "0.0", "TOV": "0.0", "PF": "4.9", "PTS": "14.7", "Awards": ""}{"Rk": "83", "Player": "Kevin Gamble", "Age": "26", "Team": "BOS", "Pos": "SF", "G": "10", "GS": "10", "MP": "335", "FG": "6.7", "FGA": "14.1", "FG%": ".473", "3P": "0.0", "3PA": "0.2", "3P%": ".000", "2P": "6.7", "2PA": "13.9", "2P%": ".481", "eFG%": ".473", "FT": "1.3", "FTA": "1.6", "FT%": ".800", "ORB": "1.4", "DRB": "3.1", "TRB": "4.5", "AST": "2.5", "STL": "1.3", "BLK": "0.6", "TOV": "1.1", "PF": "2.8", "PTS": "14.6", "Awards": ""}{"Rk": "84", "Player": "Doc Rivers", "Age": "30", "Team": "LAC", "Pos": "PG", "G": "5", "GS": "4", "MP": "187", "FG": "4.8", "FGA": "10.8", "FG%": ".446", "3P": "0.8", "3PA": "1.5", "3P%": ".500", "2P": "4.0", "2PA": "9.2", "2P%": ".438", "eFG%": ".482", "FT": "4.2", "FTA": "5.2", "FT%": ".815", "ORB": "0.8", "DRB": "2.9", "TRB": "3.7", "AST": "4.0", "STL": "1.2", "BLK": "0.0", "TOV": "0.6", "PF": "3.1", "PTS": "14.6", "Awards": ""}{"Rk": "85", "Player": "Tyrone Corbin", "Age": "29", "Team": "UTA", "Pos": "SF", "G": "16", "GS": "0", "MP": "447", "FG": "5.6", "FGA": "11.0", "FG%": ".504", "3P": "0.0", "3PA": "0.2", "3P%": ".000", "2P": "5.6", "2PA": "10.9", "2P%": ".511", "eFG%": ".504", "FT": "3.4", "FTA": "4.3", "FT%": ".778", "ORB": "3.1", "DRB": "3.9", "TRB": "7.1", "AST": "1.4", "STL": "1.0", "BLK": "0.2", "TOV": "1.4", "PF": "3.6", "PTS": "14.5", "Awards": ""}{"Rk": "86", "Player": "Dee Brown", "Age": "23", "Team": "BOS", "Pos": "PG", "G": "6", "GS": "0", "MP": "120", "FG": "6.6", "FGA": "13.2", "FG%": ".500", "3P": "0.0", "3PA": "0.9", "3P%": ".000", "2P": "6.6", "2PA": "12.3", "2P%": ".537", "eFG%": ".500", "FT": "1.2", "FTA": "1.8", "FT%": ".667", "ORB": "0.9", "DRB": "2.7", "TRB": "3.6", "AST": "9.3", "STL": "0.3", "BLK": "1.2", "TOV": "2.1", "PF": "4.8", "PTS": "14.4", "Awards": ""}{"Rk": "87", "Player": "Mark Aguirre", "Age": "32", "Team": "DET", "Pos": "SF", "G": "5", "GS": "0", "MP": "113", "FG": "5.1", "FGA": "15.3", "FG%": ".333", "3P": "0.3", "3PA": "1.6", "3P%": ".200", "2P": "4.8", "2PA": "13.7", "2P%": ".349", "eFG%": ".344", "FT": "3.8", "FTA": "5.1", "FT%": ".750", "ORB": "1.3", "DRB": "1.6", "TRB": "2.9", "AST": "3.8", "STL": "0.6", "BLK": "0.3", "TOV": "4.1", "PF": "2.9", "PTS": "14.3", "Awards": ""}{"Rk": "88", "Player": "Charles Smith", "Age": "26", "Team": "LAC", "Pos": "SF", "G": "5", "GS": "5", "MP": "148", "FG": "5.4", "FGA": "13.6", "FG%": ".393", "3P": "0.0", "3PA": "0.0", "3P%": "", "2P": "5.4", "2PA": "13.6", "2P%": ".393", "eFG%": ".393", "FT": "3.4", "FTA": "3.6", "FT%": ".933", "ORB": "2.4", "DRB": "4.4", "TRB": "6.8", "AST": "2.2", "STL": "1.0", "BLK": "2.9", "TOV": "2.4", "PF": "5.8", "PTS": "14.1", "Awards": ""}{"Rk": "89", "Player": "Rod Strickland", "Age": "25", "Team": "SAS", "Pos": "PG", "G": "2", "GS": "2", "MP": "80", "FG": "5.9", "FGA": "9.9", "FG%": ".591", "3P": "0.0", "3PA": "0.0", "3P%": "", "2P": "5.9", "2PA": "9.9", "2P%": ".591", "eFG%": ".591", "FT": "2.3", "FTA": "3.6", "FT%": ".625", "ORB": "0.0", "DRB": "3.2", "TRB": "3.2", "AST": "8.6", "STL": "1.4", "BLK": "0.9", "TOV": "2.7", "PF": "3.6", "PTS": "14.0", "Awards": ""}{"Rk": "90", "Player": "Kevin Duckworth", "Age": "27", "Team": "POR", "Pos": "C", "G": "21", "GS": "21", "MP": "647", "FG": "6.0", "FGA": "12.0", "FG%": ".495", "3P": "0.0", "3PA": "0.0", "3P%": "", "2P": "6.0", "2PA": "12.0", "2P%": ".495", "eFG%": ".495", "FT": "1.9", "FTA": "2.9", "FT%": ".660", "ORB": "2.2", "DRB": "4.3", "TRB": "6.5", "AST": "2.3", "STL": "0.6", "BLK": "0.7", "TOV": "2.5", "PF": "4.2", "PTS": "13.9", "Awards": ""}{"Rk": "91", "Player": "Joe Dumars", "Age": "28", "Team": "DET", "Pos": "SG", "G": "5", "GS": "5", "MP": "221", "FG": "5.2", "FGA": "11.1", "FG%": ".471", "3P": "0.8", "3PA": "1.6", "3P%": ".500", "2P": "4.4", "2PA": "9.4", "2P%": ".466", "eFG%": ".507", "FT": "2.4", "FTA": "3.1", "FT%": ".789", "ORB": "0.8", "DRB": "0.5", "TRB": "1.3", "AST": "2.6", "STL": "0.8", "BLK": "0.2", "TOV": "1.1", "PF": "1.8", "PTS": "13.7", "Awards": ""}{"Rk": "92", "Player": "John Stockton", "Age": "29", "Team": "UTA", "Pos": "PG", "G": "16", "GS": "16", "MP": "623", "FG": "4.4", "FGA": "10.5", "FG%": ".423", "3P": "1.0", "3PA": "3.4", "3P%": ".310", "2P": "3.4", "2PA": "7.2", "2P%": ".476", "eFG%": ".473", "FT": "3.8", "FTA": "4.5", "FT%": ".833", "ORB": "0.6", "DRB": "2.1", "TRB": "2.7", "AST": "12.5", "STL": "2.0", "BLK": "0.3", "TOV": "3.4", "PF": "2.2", "PTS": "13.7", "Awards": ""}{"Rk": "93", "Player": "B.J. Armstrong", "Age": "24", "Team": "CHI", "Pos": "PG", "G": "22", "GS": "0", "MP": "434", "FG": "5.2", "FGA": "11.5", "FG%": ".453", "3P": "0.4", "3PA": "1.4", "3P%": ".294", "2P": "4.8", "2PA": "10.1", "2P%": ".475", "eFG%": ".471", "FT": "2.5", "FTA": "3.2", "FT%": ".789", "ORB": "0.2", "DRB": "1.8", "TRB": "2.0", "AST": "3.9", "STL": "1.2", "BLK": "0.0", "TOV": "1.5", "PF": "2.7", "PTS": "13.4", "Awards": ""}{"Rk": "94", "Player": "Trent Tucker", "Age": "32", "Team": "SAS", "Pos": "SG", "G": "3", "GS": "0", "MP": "38", "FG": "5.7", "FGA": "13.3", "FG%": ".429", "3P": "0.9", "3PA": "4.7", "3P%": ".200", "2P": "4.7", "2PA": "8.5", "2P%": ".556", "eFG%": ".464", "FT": "0.9", "FTA": "0.9", "FT%": "1.000", "ORB": "0.9", "DRB": "1.9", "TRB": "2.8", "AST": "1.9", "STL": "0.0", "BLK": "0.0", "TOV": "2.8", "PF": "2.8", "PTS": "13.3", "Awards": ""}{"Rk": "95", "Player": "James Edwards", "Age": "36", "Team": "LAC", "Pos": "C", "G": "5", "GS": "0", "MP": "87", "FG": "4.1", "FGA": "9.9", "FG%": ".417", "3P": "0.0", "3PA": "0.0", "3P%": "", "2P": "4.1", "2PA": "9.9", "2P%": ".417", "eFG%": ".417", "FT": "5.0", "FTA": "7.9", "FT%": ".632", "ORB": "2.1", "DRB": "3.3", "TRB": "5.4", "AST": "1.2", "STL": "0.4", "BLK": "0.4", "TOV": "1.7", "PF": "4.6", "PTS": "13.2", "Awards": ""}{"Rk": "96", "Player": "James Donaldson", "Age": "34", "Team": "NYK", "Pos": "C", "G": "2", "GS": "0", "MP": "11", "FG": "6.5", "FGA": "6.5", "FG%": "1.000", "3P": "0.0", "3PA": "0.0", "3P%": "", "2P": "6.5", "2PA": "6.5", "2P%": "1.000", "eFG%": "1.000", "FT": "0.0", "FTA": "0.0", "FT%": "", "ORB": "0.0", "DRB": "13.1", "TRB": "13.1", "AST": "0.0", "STL": "0.0", "BLK": "3.3", "TOV": "6.5", "PF": "6.5", "PTS": "13.1", "Awards": ""}{"Rk": "97", "Player": "Blue Edwards", "Age": "26", "Team": "UTA", "Pos": "SF", "G": "16", "GS": "7", "MP": "354", "FG": "5.3", "FGA": "11.3", "FG%": ".468", "3P": "0.2", "3PA": "1.0", "3P%": ".200", "2P": "5.1", "2PA": "10.3", "2P%": ".495", "eFG%": ".477", "FT": "2.3", "FTA": "3.3", "FT%": ".719", "ORB": "2.2", "DRB": "2.9", "TRB": "5.2", "AST": "1.7", "STL": "2.3", "BLK": "0.3", "TOV": "2.5", "PF": "4.6", "PTS": "13.1", "Awards": ""}{"Rk": "98", "Player": "Sedale Threatt", "Age": "30", "Team": "LAL", "Pos": "PG", "G": "4", "GS": "4", "MP": "162", "FG": "5.3", "FGA": "10.2", "FG%": ".522", "3P": "0.4", "3PA": "0.7", "3P%": ".667", "2P": "4.9", "2PA": "9.6", "2P%": ".512", "eFG%": ".543", "FT": "2.0", "FTA": "2.7", "FT%": ".750", "ORB": "0.0", "DRB": "1.8", "TRB": "1.8", "AST": "3.8", "STL": "0.4", "BLK": "0.0", "TOV": "2.4", "PF": "2.4", "PTS": "13.1", "Awards": ""}{"Rk": "99", "Player": "Danny Young", "Age": "29", "Team": "LAC", "Pos": "PG", "G": "3", "GS": "0", "MP": "11", "FG": "6.5", "FGA": "13.1", "FG%": ".500", "3P": "0.0", "3PA": "6.5", "3P%": ".000", "2P": "6.5", "2PA": "6.5", "2P%": "1.000", "eFG%": ".500", "FT": "0.0", "FTA": "0.0", "FT%": "", "ORB": "0.0", "DRB": "0.0", "TRB": "0.0", "AST": "3.3", "STL": "0.0", "BLK": "0.0", "TOV": "6.5", "PF": "0.0", "PTS": "13.1", "Awards": ""}{"Rk": "100", "Player": "John Bagley", "Age": "31", "Team": "BOS", "Pos": "PG", "G": "10", "GS": "10", "MP": "308", "FG": "4.9", "FGA": "11.1", "FG%": ".442", "3P": "0.1", "3PA": "0.5", "3P%": ".250", "2P": "4.8", "2PA": "10.6", "2P%": ".451", "eFG%": ".447", "FT": "3.0", "FTA": "4.3", "FT%": ".703", "ORB": "0.9", "DRB": "2.2", "TRB": "3.2", "AST": "9.9", "STL": "1.1", "BLK": "0.1", "TOV": "4.1", "PF": "2.0", "PTS": "13.0", "Awards": ""}{"Rk": "101", "Player": "Vinnie Johnson", "Age": "35", "Team": "SAS", "Pos": "SG", "G": "3", "GS": "0", "MP": "69", "FG": "5.7", "FGA": "12.5", "FG%": ".458", "3P": "1.0", "3PA": "2.1", "3P%": ".500", "2P": "4.7", "2PA": "10.4", "2P%": ".450", "eFG%": ".500", "FT": "0.5", "FTA": "1.0", "FT%": ".500", "ORB": "1.6", "DRB": "2.6", "TRB": "4.2", "AST": "3.7", "STL": "2.6", "BLK": "0.5", "TOV": "2.6", "PF": "3.7", "PTS": "13.0", "Awards": ""}{"Rk": "102", "Player": "Robert Parish", "Age": "38", "Team": "BOS", "Pos": "C", "G": "10", "GS": "10", "MP": "335", "FG": "5.4", "FGA": "10.9", "FG%": ".495", "3P": "0.0", "3PA": "0.0", "3P%": "", "2P": "5.4", "2PA": "10.9", "2P%": ".495", "eFG%": ".495", "FT": "2.1", "FTA": "3.0", "FT%": ".714", "ORB": "4.1", "DRB": "6.3", "TRB": "10.4", "AST": "1.5", "STL": "0.8", "BLK": "1.6", "TOV": "1.0", "PF": "2.4", "PTS": "12.9", "Awards": ""}{"Rk": "103", "Player": "Rik Smits", "Age": "25", "Team": "IND", "Pos": "C", "G": "3", "GS": "1", "MP": "28", "FG": "5.1", "FGA": "14.1", "FG%": ".364", "3P": "0.0", "3PA": "0.0", "3P%": "", "2P": "5.1", "2PA": "14.1", "2P%": ".364", "eFG%": ".364", "FT": "2.6", "FTA": "2.6", "FT%": "1.000", "ORB": "3.9", "DRB": "3.9", "TRB": "7.7", "AST": "0.0", "STL": "2.6", "BLK": "1.3", "TOV": "3.9", "PF": "9.0", "PTS": "12.9", "Awards": ""}{"Rk": "104", "Player": "Rod Higgins", "Age": "32", "Team": "GSW", "Pos": "SF", "G": "2", "GS": "2", "MP": "17", "FG": "4.2", "FGA": "10.6", "FG%": ".400", "3P": "0.0", "3PA": "4.2", "3P%": ".000", "2P": "4.2", "2PA": "6.4", "2P%": ".667", "eFG%": ".400", "FT": "4.2", "FTA": "4.2", "FT%": "1.000", "ORB": "0.0", "DRB": "0.0", "TRB": "0.0", "AST": "2.1", "STL": "2.1", "BLK": "0.0", "TOV": "0.0", "PF": "2.1", "PTS": "12.7", "Awards": ""}{"Rk": "105", "Player": "Nate McMillan", "Age": "27", "Team": "SEA", "Pos": "PG", "G": "9", "GS": "2", "MP": "246", "FG": "5.1", "FGA": "12.1", "FG%": ".422", "3P": "0.9", "3PA": "3.8", "3P%": ".231", "2P": "4.2", "2PA": "8.3", "2P%": ".509", "eFG%": ".458", "FT": "1.5", "FTA": "2.0", "FT%": ".714", "ORB": "2.0", "DRB": "2.8", "TRB": "4.8", "AST": "9.2", "STL": "2.3", "BLK": "0.4", "TOV": "3.2", "PF": "5.1", "PTS": "12.6", "Awards": ""}{"Rk": "106", "Player": "Terry Mills", "Age": "24", "Team": "NJN", "Pos": "PF", "G": "4", "GS": "0", "MP": "77", "FG": "4.7", "FGA": "12.6", "FG%": ".370", "3P": "0.0", "3PA": "0.5", "3P%": ".000", "2P": "4.7", "2PA": "12.2", "2P%": ".385", "eFG%": ".370", "FT": "3.3", "FTA": "5.1", "FT%": ".636", "ORB": "4.2", "DRB": "7.0", "TRB": "11.2", "AST": "3.7", "STL": "0.5", "BLK": "0.9", "TOV": "3.3", "PF": "8.4", "PTS": "12.6", "Awards": ""}{"Rk": "107", "Player": "Isiah Thomas", "Age": "30", "Team": "DET", "Pos": "PG", "G": "5", "GS": "5", "MP": "200", "FG": "4.0", "FGA": "11.7", "FG%": ".338", "3P": "0.7", "3PA": "2.0", "3P%": ".364", "2P": "3.2", "2PA": "9.7", "2P%": ".333", "eFG%": ".369", "FT": "4.0", "FTA": "5.0", "FT%": ".786", "ORB": "0.5", "DRB": "4.1", "TRB": "4.7", "AST": "6.7", "STL": "0.9", "BLK": "0.0", "TOV": "2.9", "PF": "3.2", "PTS": "12.6", "Awards": ""}{"Rk": "108", "Player": "David Benoit", "Age": "23", "Team": "UTA", "Pos": "SF", "G": "13", "GS": "9", "MP": "257", "FG": "5.0", "FGA": "11.8", "FG%": ".429", "3P": "0.8", "3PA": "1.8", "3P%": ".462", "2P": "4.2", "2PA": "9.9", "2P%": ".423", "eFG%": ".464", "FT": "1.5", "FTA": "1.5", "FT%": "1.000", "ORB": "2.5", "DRB": "4.5", "TRB": "7.0", "AST": "0.8", "STL": "0.8", "BLK": "0.7", "TOV": "1.4", "PF": "4.2", "PTS": "12.5", "Awards": ""}{"Rk": "109", "Player": "Danny Ferry", "Age": "25", "Team": "CLE", "Pos": "PF", "G": "9", "GS": "0", "MP": "55", "FG": "4.6", "FGA": "9.8", "FG%": ".467", "3P": "0.7", "3PA": "2.0", "3P%": ".333", "2P": "3.9", "2PA": "7.9", "2P%": ".500", "eFG%": ".500", "FT": "2.6", "FTA": "2.6", "FT%": "1.000", "ORB": "4.6", "DRB": "5.9", "TRB": "10.5", "AST": "0.7", "STL": "0.7", "BLK": "0.7", "TOV": "1.3", "PF": "4.6", "PTS": "12.4", "Awards": ""}{"Rk": "110", "Player": "Ed Nealy", "Age": "31", "Team": "PHO", "Pos": "PF", "G": "8", "GS": "0", "MP": "67", "FG": "3.8", "FGA": "9.7", "FG%": ".389", "3P": "2.7", "3PA": "7.0", "3P%": ".385", "2P": "1.1", "2PA": "2.7", "2P%": ".400", "eFG%": ".528", "FT": "2.1", "FTA": "2.1", "FT%": "1.000", "ORB": "2.1", "DRB": "7.5", "TRB": "9.7", "AST": "2.1", "STL": "1.6", "BLK": "0.0", "TOV": "0.0", "PF": "6.4", "PTS": "12.4", "Awards": ""}{"Rk": "111", "Player": "Benoit Benjamin", "Age": "27", "Team": "SEA", "Pos": "C", "G": "9", "GS": "4", "MP": "161", "FG": "5.1", "FGA": "9.2", "FG%": ".561", "3P": "0.0", "3PA": "0.2", "3P%": ".000", "2P": "5.1", "2PA": "8.9", "2P%": ".575", "eFG%": ".561", "FT": "2.0", "FTA": "4.0", "FT%": ".500", "ORB": "2.2", "DRB": "8.0", "TRB": "10.3", "AST": "1.1", "STL": "1.1", "BLK": "2.9", "TOV": "1.8", "PF": "4.5", "PTS": "12.3", "Awards": ""}{"Rk": "112", "Player": "Elden Campbell", "Age": "23", "Team": "LAL", "Pos": "C", "G": "4", "GS": "2", "MP": "117", "FG": "4.3", "FGA": "11.4", "FG%": ".378", "3P": "0.0", "3PA": "0.0", "3P%": "", "2P": "4.3", "2PA": "11.4", "2P%": ".378", "eFG%": ".378", "FT": "3.7", "FTA": "5.5", "FT%": ".667", "ORB": "2.8", "DRB": "4.9", "TRB": "7.7", "AST": "1.8", "STL": "0.9", "BLK": "1.8", "TOV": "1.2", "PF": "4.3", "PTS": "12.3", "Awards": ""}{"Rk": "113", "Player": "Tate George", "Age": "23", "Team": "NJN", "Pos": "SG", "G": "4", "GS": "0", "MP": "44", "FG": "5.7", "FGA": "18.8", "FG%": ".304", "3P": "0.0", "3PA": "0.0", "3P%": "", "2P": "5.7", "2PA": "18.8", "2P%": ".304", "eFG%": ".304", "FT": "0.8", "FTA": "2.5", "FT%": ".333", "ORB": "0.0", "DRB": "0.0", "TRB": "0.0", "AST": "6.5", "STL": "2.5", "BLK": "0.8", "TOV": "3.3", "PF": "6.5", "PTS": "12.3", "Awards": ""}{"Rk": "114", "Player": "Alton Lister", "Age": "33", "Team": "GSW", "Pos": "C", "G": "4", "GS": "3", "MP": "47", "FG": "4.6", "FGA": "11.5", "FG%": ".400", "3P": "0.0", "3PA": "0.0", "3P%": "", "2P": "4.6", "2PA": "11.5", "2P%": ".400", "eFG%": ".400", "FT": "3.1", "FTA": "3.8", "FT%": ".800", "ORB": "2.3", "DRB": "6.1", "TRB": "8.4", "AST": "0.8", "STL": "0.0", "BLK": "3.1", "TOV": "2.3", "PF": "6.9", "PTS": "12.3", "Awards": ""}{"Rk": "115", "Player": "Ken Norman", "Age": "27", "Team": "LAC", "Pos": "SF", "G": "5", "GS": "5", "MP": "184", "FG": "5.3", "FGA": "10.4", "FG%": ".509", "3P": "0.0", "3PA": "0.4", "3P%": ".000", "2P": "5.3", "2PA": "10.0", "2P%": ".529", "eFG%": ".509", "FT": "1.8", "FTA": "3.3", "FT%": ".529", "ORB": "3.7", "DRB": "5.9", "TRB": "9.6", "AST": "2.9", "STL": "0.8", "BLK": "0.6", "TOV": "1.2", "PF": "3.5", "PTS": "12.3", "Awards": ""}{"Rk": "116", "Player": "Mike Brown", "Age": "28", "Team": "UTA", "Pos": "C", "G": "16", "GS": "0", "MP": "274", "FG": "3.9", "FGA": "9.9", "FG%": ".400", "3P": "0.0", "3PA": "0.0", "3P%": "", "2P": "3.9", "2PA": "9.9", "2P%": ".400", "eFG%": ".400", "FT": "4.2", "FTA": "5.4", "FT%": ".780", "ORB": "2.9", "DRB": "5.6", "TRB": "8.5", "AST": "1.4", "STL": "0.3", "BLK": "0.3", "TOV": "2.1", "PF": "5.6", "PTS": "12.1", "Awards": ""}{"Rk": "117", "Player": "Cliff Levingston", "Age": "31", "Team": "CHI", "Pos": "PF", "G": "22", "GS": "0", "MP": "191", "FG": "4.7", "FGA": "10.7", "FG%": ".439", "3P": "0.0", "3PA": "0.2", "3P%": ".000", "2P": "4.7", "2PA": "10.6", "2P%": ".446", "eFG%": ".439", "FT": "2.6", "FTA": "5.3", "FT%": ".500", "ORB": "3.2", "DRB": "4.5", "TRB": "7.7", "AST": "1.7", "STL": "0.8", "BLK": "1.1", "TOV": "2.1", "PF": "5.8", "PTS": "12.1", "Awards": ""}{"Rk": "118", "Player": "Kenny Anderson", "Age": "21", "Team": "NJN", "Pos": "PG", "G": "3", "GS": "0", "MP": "24", "FG": "4.5", "FGA": "13.5", "FG%": ".333", "3P": "0.0", "3PA": "0.0", "3P%": "", "2P": "4.5", "2PA": "13.5", "2P%": ".333", "eFG%": ".333", "FT": "3.0", "FTA": "3.0", "FT%": "1.000", "ORB": "1.5", "DRB": "3.0", "TRB": "4.5", "AST": "4.5", "STL": "1.5", "BLK": "0.0", "TOV": "1.5", "PF": "1.5", "PTS": "12.0", "Awards": ""}{"Rk": "119", "Player": "A.C. Green", "Age": "28", "Team": "LAL", "Pos": "PF", "G": "4", "GS": "4", "MP": "153", "FG": "3.8", "FGA": "9.2", "FG%": ".410", "3P": "0.0", "3PA": "0.0", "3P%": "", "2P": "3.8", "2PA": "9.2", "2P%": ".410", "eFG%": ".410", "FT": "4.5", "FTA": "5.4", "FT%": ".826", "ORB": "3.5", "DRB": "4.9", "TRB": "8.5", "AST": "1.6", "STL": "1.6", "BLK": "0.0", "TOV": "1.2", "PF": "2.4", "PTS": "12.0", "Awards": ""}{"Rk": "120", "Player": "Mark West", "Age": "31", "Team": "PHO", "Pos": "C", "G": "8", "GS": "0", "MP": "96", "FG": "5.2", "FGA": "7.1", "FG%": ".737", "3P": "0.0", "3PA": "0.0", "3P%": "", "2P": "5.2", "2PA": "7.1", "2P%": ".737", "eFG%": ".737", "FT": "1.5", "FTA": "3.0", "FT%": ".500", "ORB": "3.0", "DRB": "3.4", "TRB": "6.4", "AST": "0.7", "STL": "0.7", "BLK": "1.5", "TOV": "0.7", "PF": "7.9", "PTS": "12.0", "Awards": ""}{"Rk": "121", "Player": "Sam Bowie", "Age": "30", "Team": "NJN", "Pos": "C", "G": "4", "GS": "4", "MP": "112", "FG": "4.5", "FGA": "10.6", "FG%": ".424", "3P": "0.3", "3PA": "0.6", "3P%": ".500", "2P": "4.2", "2PA": "10.0", "2P%": ".419", "eFG%": ".439", "FT": "2.6", "FTA": "3.9", "FT%": ".667", "ORB": "2.6", "DRB": "3.5", "TRB": "6.1", "AST": "2.9", "STL": "1.0", "BLK": "1.0", "TOV": "1.6", "PF": "6.1", "PTS": "11.9", "Awards": ""}{"Rk": "122", "Player": "Bob Hansen", "Age": "31", "Team": "CHI", "Pos": "SG", "G": "9", "GS": "0", "MP": "69", "FG": "4.7", "FGA": "11.5", "FG%": ".409", "3P": "1.6", "3PA": "3.1", "3P%": ".500", "2P": "3.1", "2PA": "8.3", "2P%": ".375", "eFG%": ".477", "FT": "0.5", "FTA": "1.6", "FT%": ".333", "ORB": "2.1", "DRB": "2.6", "TRB": "4.7", "AST": "5.2", "STL": "0.5", "BLK": "0.0", "TOV": "1.0", "PF": "5.2", "PTS": "11.5", "Awards": ""}{"Rk": "123", "Player": "Rory Sparrow", "Age": "33", "Team": "LAL", "Pos": "PG", "G": "3", "GS": "0", "MP": "16", "FG": "2.3", "FGA": "9.0", "FG%": ".250", "3P": "0.0", "3PA": "0.0", "3P%": "", "2P": "2.3", "2PA": "9.0", "2P%": ".250", "eFG%": ".250", "FT": "6.8", "FTA": "9.0", "FT%": ".750", "ORB": "2.3", "DRB": "0.0", "TRB": "2.3", "AST": "9.0", "STL": "2.3", "BLK": "0.0", "TOV": "0.0", "PF": "11.3", "PTS": "11.3", "Awards": ""}{"Rk": "124", "Player": "Mike Sanders", "Age": "31", "Team": "CLE", "Pos": "SF", "G": "17", "GS": "17", "MP": "418", "FG": "4.8", "FGA": "9.9", "FG%": ".487", "3P": "0.1", "3PA": "0.3", "3P%": ".333", "2P": "4.7", "2PA": "9.6", "2P%": ".491", "eFG%": ".491", "FT": "1.5", "FTA": "1.8", "FT%": ".810", "ORB": "1.7", "DRB": "3.0", "TRB": "4.7", "AST": "3.2", "STL": "1.3", "BLK": "1.0", "TOV": "2.0", "PF": "5.3", "PTS": "11.2", "Awards": ""}{"Rk": "125", "Player": "Gerald Wilkins", "Age": "28", "Team": "NYK", "Pos": "SG", "G": "12", "GS": "12", "MP": "344", "FG": "4.7", "FGA": "11.4", "FG%": ".413", "3P": "0.1", "3PA": "1.4", "3P%": ".077", "2P": "4.6", "2PA": "10.0", "2P%": ".458", "eFG%": ".417", "FT": "1.7", "FTA": "2.4", "FT%": ".696", "ORB": "1.3", "DRB": "1.9", "TRB": "3.1", "AST": "3.6", "STL": "0.5", "BLK": "0.1", "TOV": "1.6", "PF": "3.7", "PTS": "11.2", "Awards": ""}{"Rk": "126", "Player": "Grant Long", "Age": "25", "Team": "MIA", "Pos": "PF", "G": "3", "GS": "3", "MP": "120", "FG": "4.5", "FGA": "10.8", "FG%": ".417", "3P": "0.0", "3PA": "1.2", "3P%": ".000", "2P": "4.5", "2PA": "9.6", "2P%": ".469", "eFG%": ".417", "FT": "2.1", "FTA": "3.0", "FT%": ".700", "ORB": "2.1", "DRB": "2.4", "TRB": "4.5", "AST": "2.4", "STL": "1.5", "BLK": "0.0", "TOV": "1.5", "PF": "3.3", "PTS": "11.1", "Awards": ""}{"Rk": "127", "Player": "Craig Hodges", "Age": "31", "Team": "CHI", "Pos": "SG", "G": "17", "GS": "0", "MP": "137", "FG": "4.2", "FGA": "10.8", "FG%": ".390", "3P": "2.4", "3PA": "5.3", "3P%": ".450", "2P": "1.8", "2PA": "5.5", "2P%": ".333", "eFG%": ".500", "FT": "0.3", "FTA": "0.5", "FT%": ".500", "ORB": "0.8", "DRB": "0.3", "TRB": "1.1", "AST": "1.3", "STL": "1.3", "BLK": "0.0", "TOV": "2.1", "PF": "2.6", "PTS": "11.0", "Awards": ""}{"Rk": "128", "Player": "Ed Pinckney", "Age": "28", "Team": "BOS", "Pos": "PF", "G": "10", "GS": "8", "MP": "314", "FG": "4.0", "FGA": "6.6", "FG%": ".603", "3P": "0.0", "3PA": "0.1", "3P%": ".000", "2P": "4.0", "2PA": "6.5", "2P%": ".614", "eFG%": ".603", "FT": "3.0", "FTA": "3.6", "FT%": ".839", "ORB": "4.1", "DRB": "5.5", "TRB": "9.6", "AST": "0.8", "STL": "1.4", "BLK": "1.0", "TOV": "1.5", "PF": "3.4", "PTS": "11.0", "Awards": ""}{"Rk": "129", "Player": "Terrell Brandon", "Age": "21", "Team": "CLE", "Pos": "PG", "G": "12", "GS": "0", "MP": "157", "FG": "5.0", "FGA": "12.6", "FG%": ".400", "3P": "0.0", "3PA": "0.7", "3P%": ".000", "2P": "5.0", "2PA": "11.9", "2P%": ".423", "eFG%": ".400", "FT": "0.7", "FTA": "0.9", "FT%": ".750", "ORB": "0.9", "DRB": "4.1", "TRB": "5.0", "AST": "6.9", "STL": "0.7", "BLK": "0.2", "TOV": "2.5", "PF": "3.9", "PTS": "10.8", "Awards": ""}{"Rk": "130", "Player": "Delaney Rudd", "Age": "29", "Team": "UTA", "Pos": "SG", "G": "10", "GS": "0", "MP": "84", "FG": "4.3", "FGA": "9.0", "FG%": ".476", "3P": "0.9", "3PA": "3.0", "3P%": ".286", "2P": "3.4", "2PA": "6.0", "2P%": ".571", "eFG%": ".524", "FT": "1.3", "FTA": "1.7", "FT%": ".750", "ORB": "0.0", "DRB": "1.7", "TRB": "1.7", "AST": "8.1", "STL": "1.3", "BLK": "0.0", "TOV": "1.7", "PF": "4.7", "PTS": "10.7", "Awards": ""}{"Rk": "131", "Player": "Greg Anthony", "Age": "24", "Team": "NYK", "Pos": "PG", "G": "12", "GS": "0", "MP": "213", "FG": "3.2", "FGA": "7.8", "FG%": ".413", "3P": "0.8", "3PA": "2.0", "3P%": ".417", "2P": "2.4", "2PA": "5.7", "2P%": ".412", "eFG%": ".467", "FT": "3.4", "FTA": "5.6", "FT%": ".606", "ORB": "0.7", "DRB": "2.2", "TRB": "2.9", "AST": "6.9", "STL": "2.7", "BLK": "0.2", "TOV": "2.2", "PF": "4.7", "PTS": "10.6", "Awards": ""}{"Rk": "132", "Player": "Craig Ehlo", "Age": "30", "Team": "CLE", "Pos": "SG", "G": "17", "GS": "14", "MP": "552", "FG": "4.1", "FGA": "9.9", "FG%": ".414", "3P": "1.4", "3PA": "3.3", "3P%": ".412", "2P": "2.7", "2PA": "6.6", "2P%": ".416", "eFG%": ".484", "FT": "1.0", "FTA": "1.4", "FT%": ".762", "ORB": "1.4", "DRB": "3.6", "TRB": "5.0", "AST": "5.0", "STL": "1.4", "BLK": "0.3", "TOV": "1.2", "PF": "2.6", "PTS": "10.6", "Awards": ""}{"Rk": "133", "Player": "Steve Kerr", "Age": "26", "Team": "CLE", "Pos": "PG", "G": "12", "GS": "3", "MP": "149", "FG": "4.3", "FGA": "9.9", "FG%": ".439", "3P": "0.7", "3PA": "2.7", "3P%": ".273", "2P": "3.6", "2PA": "7.2", "2P%": ".500", "eFG%": ".476", "FT": "1.2", "FTA": "1.2", "FT%": "1.000", "ORB": "0.2", "DRB": "1.2", "TRB": "1.4", "AST": "2.4", "STL": "1.2", "BLK": "0.0", "TOV": "1.0", "PF": "2.9", "PTS": "10.6", "Awards": ""}{"Rk": "134", "Player": "Victor Alexander", "Age": "22", "Team": "GSW", "Pos": "C", "G": "4", "GS": "0", "MP": "24", "FG": "4.5", "FGA": "7.5", "FG%": ".600", "3P": "0.0", "3PA": "0.0", "3P%": "", "2P": "4.5", "2PA": "7.5", "2P%": ".600", "eFG%": ".600", "FT": "1.5", "FTA": "1.5", "FT%": "1.000", "ORB": "1.5", "DRB": "7.5", "TRB": "9.0", "AST": "1.5", "STL": "3.0", "BLK": "0.0", "TOV": "3.0", "PF": "12.0", "PTS": "10.5", "Awards": ""}{"Rk": "135", "Player": "Sherman Douglas", "Age": "25", "Team": "BOS", "Pos": "PG", "G": "6", "GS": "0", "MP": "65", "FG": "5.0", "FGA": "13.8", "FG%": ".360", "3P": "0.0", "3PA": "1.1", "3P%": ".000", "2P": "5.0", "2PA": "12.7", "2P%": ".391", "eFG%": ".360", "FT": "0.6", "FTA": "1.1", "FT%": ".500", "ORB": "0.6", "DRB": "1.7", "TRB": "2.2", "AST": "5.5", "STL": "0.0", "BLK": "0.0", "TOV": "2.2", "PF": "4.4", "PTS": "10.5", "Awards": ""}{"Rk": "136", "Player": "Horace Grant", "Age": "26", "Team": "CHI", "Pos": "PF", "G": "22", "GS": "22", "MP": "856", "FG": "4.2", "FGA": "7.7", "FG%": ".541", "3P": "0.0", "3PA": "0.1", "3P%": ".000", "2P": "4.2", "2PA": "7.6", "2P%": ".547", "eFG%": ".541", "FT": "2.1", "FTA": "3.2", "FT%": ".671", "ORB": "3.2", "DRB": "5.0", "TRB": "8.2", "AST": "2.8", "STL": "1.0", "BLK": "1.6", "TOV": "0.9", "PF": "2.9", "PTS": "10.5", "Awards": ""}{"Rk": "137", "Player": "John Paxson", "Age": "31", "Team": "CHI", "Pos": "PG", "G": "22", "GS": "22", "MP": "598", "FG": "4.4", "FGA": "8.4", "FG%": ".525", "3P": "0.7", "3PA": "1.6", "3P%": ".444", "2P": "3.7", "2PA": "6.7", "2P%": ".545", "eFG%": ".568", "FT": "1.0", "FTA": "1.1", "FT%": ".842", "ORB": "0.0", "DRB": "1.3", "TRB": "1.3", "AST": "3.7", "STL": "0.8", "BLK": "0.1", "TOV": "0.8", "PF": "3.2", "PTS": "10.5", "Awards": ""}{"Rk": "138", "Player": "Gary Grant", "Age": "26", "Team": "LAC", "Pos": "PG", "G": "5", "GS": "1", "MP": "77", "FG": "4.7", "FGA": "9.8", "FG%": ".476", "3P": "0.0", "3PA": "0.9", "3P%": ".000", "2P": "4.7", "2PA": "8.9", "2P%": ".526", "eFG%": ".476", "FT": "0.9", "FTA": "0.9", "FT%": "1.000", "ORB": "0.0", "DRB": "1.9", "TRB": "1.9", "AST": "8.4", "STL": "1.4", "BLK": "0.9", "TOV": "3.7", "PF": "4.7", "PTS": "10.3", "Awards": ""}{"Rk": "139", "Player": "Will Perdue", "Age": "26", "Team": "CHI", "Pos": "C", "G": "18", "GS": "0", "MP": "157", "FG": "4.1", "FGA": "8.5", "FG%": ".486", "3P": "0.0", "3PA": "0.2", "3P%": ".000", "2P": "4.1", "2PA": "8.3", "2P%": ".500", "eFG%": ".486", "FT": "2.1", "FTA": "4.6", "FT%": ".450", "ORB": "4.1", "DRB": "5.0", "TRB": "9.2", "AST": "2.1", "STL": "0.7", "BLK": "2.3", "TOV": "2.8", "PF": "7.8", "PTS": "10.3", "Awards": ""}{"Rk": "140", "Player": "Bill Laimbeer", "Age": "34", "Team": "DET", "Pos": "C", "G": "5", "GS": "4", "MP": "145", "FG": "4.2", "FGA": "11.4", "FG%": ".370", "3P": "0.5", "3PA": "2.5", "3P%": ".200", "2P": "3.7", "2PA": "8.9", "2P%": ".417", "eFG%": ".391", "FT": "1.2", "FTA": "1.2", "FT%": "1.000", "ORB": "1.2", "DRB": "7.0", "TRB": "8.2", "AST": "2.0", "STL": "1.0", "BLK": "0.2", "TOV": "1.2", "PF": "4.5", "PTS": "10.2", "Awards": ""}{"Rk": "141", "Player": "Paul Pressey", "Age": "33", "Team": "SAS", "Pos": "SG", "G": "3", "GS": "2", "MP": "46", "FG": "4.7", "FGA": "14.1", "FG%": ".333", "3P": "0.8", "3PA": "1.6", "3P%": ".500", "2P": "3.9", "2PA": "12.5", "2P%": ".313", "eFG%": ".361", "FT": "0.0", "FTA": "0.0", "FT%": "", "ORB": "0.8", "DRB": "1.6", "TRB": "2.3", "AST": "2.3", "STL": "2.3", "BLK": "0.8", "TOV": "3.9", "PF": "7.0", "PTS": "10.2", "Awards": ""}{"Rk": "142", "Player": "Gary Payton", "Age": "23", "Team": "SEA", "Pos": "PG", "G": "8", "GS": "8", "MP": "221", "FG": "4.4", "FGA": "9.4", "FG%": ".466", "3P": "0.0", "3PA": "0.3", "3P%": ".000", "2P": "4.4", "2PA": "9.1", "2P%": ".482", "eFG%": ".466", "FT": "1.1", "FTA": "2.0", "FT%": ".583", "ORB": "1.0", "DRB": "2.4", "TRB": "3.4", "AST": "6.2", "STL": "1.3", "BLK": "0.3", "TOV": "1.6", "PF": "4.2", "PTS": "9.9", "Awards": ""}{"Rk": "143", "Player": "Scott Williams", "Age": "23", "Team": "CHI", "Pos": "PF", "G": "22", "GS": "0", "MP": "321", "FG": "3.8", "FGA": "7.9", "FG%": ".486", "3P": "0.0", "3PA": "0.1", "3P%": ".000", "2P": "3.8", "2PA": "7.7", "2P%": ".493", "eFG%": ".486", "FT": "2.2", "FTA": "3.1", "FT%": ".714", "ORB": "3.7", "DRB": "7.0", "TRB": "10.7", "AST": "0.8", "STL": "0.7", "BLK": "2.0", "TOV": "1.7", "PF": "7.3", "PTS": "9.9", "Awards": ""}{"Rk": "144", "Player": "Vlade Divac", "Age": "23", "Team": "LAL", "Pos": "C", "G": "4", "GS": "4", "MP": "143", "FG": "3.8", "FGA": "10.8", "FG%": ".349", "3P": "0.0", "3PA": "0.5", "3P%": ".000", "2P": "3.8", "2PA": "10.3", "2P%": ".366", "eFG%": ".349", "FT": "2.3", "FTA": "2.5", "FT%": ".900", "ORB": "1.5", "DRB": "4.0", "TRB": "5.5", "AST": "3.8", "STL": "1.3", "BLK": "0.8", "TOV": "4.5", "PF": "4.3", "PTS": "9.8", "Awards": ""}{"Rk": "145", "Player": "Kevin Edwards", "Age": "26", "Team": "MIA", "Pos": "PG", "G": "3", "GS": "0", "MP": "55", "FG": "3.3", "FGA": "8.5", "FG%": ".385", "3P": "0.0", "3PA": "0.0", "3P%": "", "2P": "3.3", "2PA": "8.5", "2P%": ".385", "eFG%": ".385", "FT": "3.3", "FTA": "5.2", "FT%": ".625", "ORB": "0.7", "DRB": "3.9", "TRB": "4.6", "AST": "4.6", "STL": "1.3", "BLK": "0.0", "TOV": "3.3", "PF": "2.0", "PTS": "9.8", "Awards": ""}{"Rk": "146", "Player": "Mark Jackson", "Age": "26", "Team": "NYK", "Pos": "PG", "G": "12", "GS": "12", "MP": "368", "FG": "3.6", "FGA": "9.0", "FG%": ".402", "3P": "0.4", "3PA": "2.1", "3P%": ".190", "2P": "3.2", "2PA": "6.9", "2P%": ".465", "eFG%": ".424", "FT": "2.2", "FTA": "2.6", "FT%": ".815", "ORB": "1.2", "DRB": "1.5", "TRB": "2.6", "AST": "8.4", "STL": "1.0", "BLK": "0.0", "TOV": "2.9", "PF": "2.5", "PTS": "9.8", "Awards": ""}{"Rk": "147", "Player": "Keith Askins", "Age": "24", "Team": "MIA", "Pos": "SF", "G": "3", "GS": "0", "MP": "48", "FG": "3.7", "FGA": "8.2", "FG%": ".455", "3P": "2.3", "3PA": "3.7", "3P%": ".600", "2P": "1.5", "2PA": "4.5", "2P%": ".333", "eFG%": ".591", "FT": "0.0", "FTA": "1.5", "FT%": ".000", "ORB": "3.0", "DRB": "3.8", "TRB": "6.8", "AST": "2.3", "STL": "0.7", "BLK": "0.0", "TOV": "0.7", "PF": "5.2", "PTS": "9.7", "Awards": ""}{"Rk": "148", "Player": "Donald Royal", "Age": "25", "Team": "SAS", "Pos": "SF", "G": "3", "GS": "2", "MP": "57", "FG": "3.2", "FGA": "5.7", "FG%": ".556", "3P": "0.0", "3PA": "0.0", "3P%": "", "2P": "3.2", "2PA": "5.7", "2P%": ".556", "eFG%": ".556", "FT": "3.2", "FTA": "5.7", "FT%": ".556", "ORB": "3.2", "DRB": "4.4", "TRB": "7.6", "AST": "0.0", "STL": "1.3", "BLK": "1.3", "TOV": "3.8", "PF": "4.4", "PTS": "9.5", "Awards": ""}{"Rk": "149", "Player": "Buck Williams", "Age": "31", "Team": "POR", "Pos": "PF", "G": "21", "GS": "21", "MP": "758", "FG": "3.1", "FGA": "6.2", "FG%": ".508", "3P": "0.0", "3PA": "0.0", "3P%": "", "2P": "3.1", "2PA": "6.2", "2P%": ".508", "eFG%": ".508", "FT": "3.3", "FTA": "4.3", "FT%": ".758", "ORB": "2.9", "DRB": "5.6", "TRB": "8.5", "AST": "1.0", "STL": "1.3", "BLK": "0.8", "TOV": "2.1", "PF": "3.5", "PTS": "9.5", "Awards": ""}{"Rk": "150", "Player": "Mookie Blaylock", "Age": "24", "Team": "NJN", "Pos": "PG", "G": "4", "GS": "4", "MP": "148", "FG": "4.1", "FGA": "13.4", "FG%": ".309", "3P": "0.2", "3PA": "1.5", "3P%": ".167", "2P": "3.9", "2PA": "11.9", "2P%": ".327", "eFG%": ".318", "FT": "0.7", "FTA": "1.0", "FT%": ".750", "ORB": "1.2", "DRB": "2.7", "TRB": "3.9", "AST": "7.5", "STL": "3.6", "BLK": "0.5", "TOV": "1.7", "PF": "3.9", "PTS": "9.2", "Awards": ""}{"Rk": "151", "Player": "Olden Polynice", "Age": "27", "Team": "LAC", "Pos": "C", "G": "5", "GS": "0", "MP": "63", "FG": "4.0", "FGA": "6.9", "FG%": ".583", "3P": "0.0", "3PA": "0.0", "3P%": "", "2P": "4.0", "2PA": "6.9", "2P%": ".583", "eFG%": ".583", "FT": "1.1", "FTA": "3.4", "FT%": ".333", "ORB": "1.1", "DRB": "9.1", "TRB": "10.3", "AST": "1.1", "STL": "0.6", "BLK": "0.6", "TOV": "0.6", "PF": "6.3", "PTS": "9.1", "Awards": ""}{"Rk": "152", "Player": "LaSalle Thompson", "Age": "30", "Team": "IND", "Pos": "C", "G": "3", "GS": "3", "MP": "63", "FG": "4.0", "FGA": "6.3", "FG%": ".636", "3P": "0.0", "3PA": "0.0", "3P%": "", "2P": "4.0", "2PA": "6.3", "2P%": ".636", "eFG%": ".636", "FT": "1.1", "FTA": "1.1", "FT%": "1.000", "ORB": "1.1", "DRB": "6.3", "TRB": "7.4", "AST": "2.3", "STL": "0.6", "BLK": "2.3", "TOV": "1.7", "PF": "6.3", "PTS": "9.1", "Awards": ""}{"Rk": "153", "Player": "Joe Kleine", "Age": "30", "Team": "BOS", "Pos": "C", "G": "9", "GS": "0", "MP": "82", "FG": "4.0", "FGA": "9.7", "FG%": ".409", "3P": "0.0", "3PA": "0.4", "3P%": ".000", "2P": "4.0", "2PA": "9.2", "2P%": ".429", "eFG%": ".409", "FT": "0.9", "FTA": "0.9", "FT%": "1.000", "ORB": "2.6", "DRB": "7.0", "TRB": "9.7", "AST": "0.4", "STL": "0.0", "BLK": "0.4", "TOV": "1.3", "PF": "4.8", "PTS": "8.8", "Awards": ""}{"Rk": "154", "Player": "Andrew Lang", "Age": "25", "Team": "PHO", "Pos": "C", "G": "8", "GS": "8", "MP": "192", "FG": "2.8", "FGA": "7.5", "FG%": ".375", "3P": "0.0", "3PA": "0.0", "3P%": "", "2P": "2.8", "2PA": "7.5", "2P%": ".375", "eFG%": ".375", "FT": "2.8", "FTA": "3.6", "FT%": ".789", "ORB": "2.8", "DRB": "3.2", "TRB": "6.0", "AST": "0.4", "STL": "0.6", "BLK": "2.8", "TOV": "1.5", "PF": "6.2", "PTS": "8.4", "Awards": ""}{"Rk": "155", "Player": "Dennis Rodman", "Age": "30", "Team": "DET", "Pos": "PF", "G": "5", "GS": "5", "MP": "156", "FG": "3.7", "FGA": "6.2", "FG%": ".593", "3P": "0.0", "3PA": "0.5", "3P%": ".000", "2P": "3.7", "2PA": "5.8", "2P%": ".640", "eFG%": ".593", "FT": "0.9", "FTA": "1.8", "FT%": ".500", "ORB": "3.7", "DRB": "8.1", "TRB": "11.8", "AST": "2.1", "STL": "0.9", "BLK": "0.5", "TOV": "1.6", "PF": "3.9", "PTS": "8.3", "Awards": ""}{"Rk": "156", "Player": "Bob Thornton", "Age": "29", "Team": "UTA", "Pos": "PF", "G": "7", "GS": "0", "MP": "32", "FG": "2.3", "FGA": "5.6", "FG%": ".400", "3P": "0.0", "3PA": "0.0", "3P%": "", "2P": "2.3", "2PA": "5.6", "2P%": ".400", "eFG%": ".400", "FT": "3.4", "FTA": "4.5", "FT%": ".750", "ORB": "4.5", "DRB": "5.6", "TRB": "10.1", "AST": "1.1", "STL": "0.0", "BLK": "0.0", "TOV": "1.1", "PF": "3.4", "PTS": "7.9", "Awards": ""}{"Rk": "157", "Player": "Robert Pack", "Age": "22", "Team": "POR", "Pos": "PG", "G": "14", "GS": "0", "MP": "52", "FG": "2.8", "FGA": "12.5", "FG%": ".222", "3P": "0.0", "3PA": "0.0", "3P%": "", "2P": "2.8", "2PA": "12.5", "2P%": ".222", "eFG%": ".222", "FT": "2.1", "FTA": "2.8", "FT%": ".750", "ORB": "1.4", "DRB": "2.8", "TRB": "4.2", "AST": "4.8", "STL": "3.5", "BLK": "0.7", "TOV": "2.1", "PF": "6.9", "PTS": "7.6", "Awards": ""}{"Rk": "158", "Player": "Anthony Mason", "Age": "25", "Team": "NYK", "Pos": "PF", "G": "12", "GS": "0", "MP": "288", "FG": "2.4", "FGA": "5.4", "FG%": ".442", "3P": "0.0", "3PA": "0.0", "3P%": "", "2P": "2.4", "2PA": "5.4", "2P%": ".442", "eFG%": ".442", "FT": "2.7", "FTA": "3.5", "FT%": ".786", "ORB": "3.5", "DRB": "6.0", "TRB": "9.5", "AST": "1.2", "STL": "0.2", "BLK": "1.0", "TOV": "1.4", "PF": "4.2", "PTS": "7.5", "Awards": ""}{"Rk": "159", "Player": "Lance Blanks", "Age": "25", "Team": "DET", "Pos": "SG", "G": "1", "GS": "0", "MP": "10", "FG": "3.6", "FGA": "7.2", "FG%": ".500", "3P": "0.0", "3PA": "0.0", "3P%": "", "2P": "3.6", "2PA": "7.2", "2P%": ".500", "eFG%": ".500", "FT": "0.0", "FTA": "0.0", "FT%": "", "ORB": "0.0", "DRB": "3.6", "TRB": "3.6", "AST": "10.8", "STL": "10.8", "BLK": "0.0", "TOV": "3.6", "PF": "7.2", "PTS": "7.2", "Awards": ""}{"Rk": "160", "Player": "Bill Cartwright", "Age": "34", "Team": "CHI", "Pos": "C", "G": "22", "GS": "22", "MP": "612", "FG": "3.2", "FGA": "6.8", "FG%": ".474", "3P": "0.0", "3PA": "0.0", "3P%": "", "2P": "3.2", "2PA": "6.8", "2P%": ".474", "eFG%": ".474", "FT": "0.8", "FTA": "1.8", "FT%": ".419", "ORB": "1.7", "DRB": "4.1", "TRB": "5.8", "AST": "2.2", "STL": "0.6", "BLK": "0.2", "TOV": "1.6", "PF": "4.1", "PTS": "7.2", "Awards": ""}{"Rk": "161", "Player": "Alan Ogg", "Age": "24", "Team": "MIA", "Pos": "C", "G": "3", "GS": "0", "MP": "15", "FG": "2.4", "FGA": "7.2", "FG%": ".333", "3P": "0.0", "3PA": "0.0", "3P%": "", "2P": "2.4", "2PA": "7.2", "2P%": ".333", "eFG%": ".333", "FT": "2.4", "FTA": "4.8", "FT%": ".500", "ORB": "0.0", "DRB": "2.4", "TRB": "2.4", "AST": "0.0", "STL": "2.4", "BLK": "7.2", "TOV": "0.0", "PF": "7.2", "PTS": "7.2", "Awards": ""}{"Rk": "162", "Player": "Mark Bryant", "Age": "26", "Team": "POR", "Pos": "PF", "G": "12", "GS": "0", "MP": "116", "FG": "3.1", "FGA": "9.0", "FG%": ".345", "3P": "0.0", "3PA": "0.0", "3P%": "", "2P": "3.1", "2PA": "9.0", "2P%": ".345", "eFG%": ".345", "FT": "0.9", "FTA": "1.2", "FT%": ".750", "ORB": "3.4", "DRB": "5.6", "TRB": "9.0", "AST": "0.3", "STL": "0.9", "BLK": "0.0", "TOV": "2.8", "PF": "6.8", "PTS": "7.1", "Awards": ""}{"Rk": "163", "Player": "Michael Cage", "Age": "30", "Team": "SEA", "Pos": "PF", "G": "9", "GS": "4", "MP": "197", "FG": "3.5", "FGA": "6.2", "FG%": ".559", "3P": "0.0", "3PA": "0.0", "3P%": "", "2P": "3.5", "2PA": "6.2", "2P%": ".559", "eFG%": ".559", "FT": "0.2", "FTA": "0.2", "FT%": "1.000", "ORB": "3.3", "DRB": "6.0", "TRB": "9.3", "AST": "0.7", "STL": "1.1", "BLK": "1.5", "TOV": "1.5", "PF": "4.0", "PTS": "7.1", "Awards": ""}{"Rk": "164", "Player": "Sidney Green", "Age": "31", "Team": "SAS", "Pos": "PF", "G": "3", "GS": "0", "MP": "47", "FG": "2.3", "FGA": "7.7", "FG%": ".300", "3P": "0.0", "3PA": "0.0", "3P%": "", "2P": "2.3", "2PA": "7.7", "2P%": ".300", "eFG%": ".300", "FT": "2.3", "FTA": "3.1", "FT%": ".750", "ORB": "3.8", "DRB": "4.6", "TRB": "8.4", "AST": "1.5", "STL": "0.0", "BLK": "0.0", "TOV": "1.5", "PF": "4.6", "PTS": "6.9", "Awards": ""}{"Rk": "165", "Player": "Chris Dudley", "Age": "26", "Team": "NJN", "Pos": "C", "G": "4", "GS": "0", "MP": "77", "FG": "2.3", "FGA": "6.5", "FG%": ".357", "3P": "0.0", "3PA": "0.0", "3P%": "", "2P": "2.3", "2PA": "6.5", "2P%": ".357", "eFG%": ".357", "FT": "1.9", "FTA": "3.7", "FT%": ".500", "ORB": "6.1", "DRB": "5.6", "TRB": "11.7", "AST": "1.4", "STL": "0.9", "BLK": "4.7", "TOV": "0.5", "PF": "6.5", "PTS": "6.5", "Awards": ""}{"Rk": "166", "Player": "Henry James", "Age": "26", "Team": "CLE", "Pos": "SF", "G": "8", "GS": "0", "MP": "22", "FG": "1.6", "FGA": "16.4", "FG%": ".100", "3P": "0.0", "3PA": "4.9", "3P%": ".000", "2P": "1.6", "2PA": "11.5", "2P%": ".143", "eFG%": ".100", "FT": "3.3", "FTA": "6.5", "FT%": ".500", "ORB": "1.6", "DRB": "1.6", "TRB": "3.3", "AST": "3.3", "STL": "1.6", "BLK": "0.0", "TOV": "1.6", "PF": "3.3", "PTS": "6.5", "Awards": ""}{"Rk": "167", "Player": "Charles Oakley", "Age": "28", "Team": "NYK", "Pos": "PF", "G": "12", "GS": "12", "MP": "354", "FG": "2.2", "FGA": "5.9", "FG%": ".379", "3P": "0.0", "3PA": "0.0", "3P%": "", "2P": "2.2", "2PA": "5.9", "2P%": ".379", "eFG%": ".379", "FT": "2.0", "FTA": "2.7", "FT%": ".741", "ORB": "4.5", "DRB": "6.5", "TRB": "11.0", "AST": "0.8", "STL": "0.8", "BLK": "0.5", "TOV": "1.5", "PF": "3.7", "PTS": "6.5", "Awards": ""}{"Rk": "168", "Player": "Tony Smith", "Age": "23", "Team": "LAL", "Pos": "PG", "G": "4", "GS": "0", "MP": "40", "FG": "2.7", "FGA": "9.0", "FG%": ".300", "3P": "0.0", "3PA": "1.8", "3P%": ".000", "2P": "2.7", "2PA": "7.2", "2P%": ".375", "eFG%": ".300", "FT": "0.9", "FTA": "1.8", "FT%": ".500", "ORB": "0.9", "DRB": "0.9", "TRB": "1.8", "AST": "4.5", "STL": "3.6", "BLK": "0.0", "TOV": "2.7", "PF": "4.5", "PTS": "6.3", "Awards": ""}{"Rk": "169", "Player": "Jack Haley", "Age": "28", "Team": "LAL", "Pos": "C", "G": "2", "GS": "0", "MP": "12", "FG": "3.0", "FGA": "12.0", "FG%": ".250", "3P": "0.0", "3PA": "0.0", "3P%": "", "2P": "3.0", "2PA": "12.0", "2P%": ".250", "eFG%": ".250", "FT": "0.0", "FTA": "0.0", "FT%": "", "ORB": "3.0", "DRB": "0.0", "TRB": "3.0", "AST": "3.0", "STL": "0.0", "BLK": "0.0", "TOV": "0.0", "PF": "9.0", "PTS": "6.0", "Awards": ""}{"Rk": "170", "Player": "Alec Kessler", "Age": "25", "Team": "MIA", "Pos": "PF", "G": "2", "GS": "0", "MP": "12", "FG": "0.0", "FGA": "6.0", "FG%": ".000", "3P": "0.0", "3PA": "0.0", "3P%": "", "2P": "0.0", "2PA": "6.0", "2P%": ".000", "eFG%": ".000", "FT": "6.0", "FTA": "6.0", "FT%": "1.000", "ORB": "0.0", "DRB": "3.0", "TRB": "3.0", "AST": "0.0", "STL": "0.0", "BLK": "0.0", "TOV": "3.0", "PF": "3.0", "PTS": "6.0", "Awards": ""}{"Rk": "171", "Player": "Ennis Whatley", "Age": "29", "Team": "POR", "Pos": "PG", "G": "15", "GS": "0", "MP": "96", "FG": "2.3", "FGA": "7.5", "FG%": ".300", "3P": "0.0", "3PA": "0.4", "3P%": ".000", "2P": "2.3", "2PA": "7.1", "2P%": ".316", "eFG%": ".300", "FT": "1.5", "FTA": "1.5", "FT%": "1.000", "ORB": "0.0", "DRB": "3.7", "TRB": "3.7", "AST": "4.9", "STL": "2.6", "BLK": "0.0", "TOV": "1.5", "PF": "4.1", "PTS": "6.0", "Awards": ""}{"Rk": "172", "Player": "Mark Eaton", "Age": "35", "Team": "UTA", "Pos": "C", "G": "16", "GS": "16", "MP": "473", "FG": "2.0", "FGA": "3.5", "FG%": ".565", "3P": "0.0", "3PA": "0.0", "3P%": "", "2P": "2.0", "2PA": "3.5", "2P%": ".565", "eFG%": ".565", "FT": "1.6", "FTA": "2.1", "FT%": ".778", "ORB": "2.3", "DRB": "4.6", "TRB": "6.8", "AST": "0.3", "STL": "0.5", "BLK": "2.7", "TOV": "0.8", "PF": "3.6", "PTS": "5.6", "Awards": ""}{"Rk": "173", "Player": "Wayne Cooper", "Age": "35", "Team": "POR", "Pos": "C", "G": "3", "GS": "0", "MP": "27", "FG": "2.7", "FGA": "5.3", "FG%": ".500", "3P": "0.0", "3PA": "0.0", "3P%": "", "2P": "2.7", "2PA": "5.3", "2P%": ".500", "eFG%": ".500", "FT": "0.0", "FTA": "0.0", "FT%": "", "ORB": "1.3", "DRB": "9.3", "TRB": "10.7", "AST": "0.0", "STL": "0.0", "BLK": "4.0", "TOV": "1.3", "PF": "5.3", "PTS": "5.3", "Awards": ""}{"Rk": "174", "Player": "Darrell Walker", "Age": "30", "Team": "DET", "Pos": "SG", "G": "5", "GS": "0", "MP": "68", "FG": "1.6", "FGA": "4.8", "FG%": ".333", "3P": "0.0", "3PA": "0.0", "3P%": "", "2P": "1.6", "2PA": "4.8", "2P%": ".333", "eFG%": ".333", "FT": "2.1", "FTA": "2.1", "FT%": "1.000", "ORB": "2.6", "DRB": "3.7", "TRB": "6.4", "AST": "2.1", "STL": "0.5", "BLK": "0.0", "TOV": "2.6", "PF": "3.7", "PTS": "5.3", "Awards": ""}{"Rk": "175", "Player": "Tyrone Hill", "Age": "23", "Team": "GSW", "Pos": "C", "G": "4", "GS": "1", "MP": "47", "FG": "2.3", "FGA": "5.4", "FG%": ".429", "3P": "0.0", "3PA": "0.0", "3P%": "", "2P": "2.3", "2PA": "5.4", "2P%": ".429", "eFG%": ".429", "FT": "0.0", "FTA": "1.5", "FT%": ".000", "ORB": "2.3", "DRB": "3.8", "TRB": "6.1", "AST": "0.8", "STL": "1.5", "BLK": "0.0", "TOV": "2.3", "PF": "9.2", "PTS": "4.6", "Awards": ""}{"Rk": "176", "Player": "Dale Davis", "Age": "22", "Team": "IND", "Pos": "PF", "G": "3", "GS": "0", "MP": "69", "FG": "2.1", "FGA": "5.2", "FG%": ".400", "3P": "0.0", "3PA": "0.0", "3P%": "", "2P": "2.1", "2PA": "5.2", "2P%": ".400", "eFG%": ".400", "FT": "0.0", "FTA": "0.0", "FT%": "", "ORB": "2.6", "DRB": "7.3", "TRB": "9.9", "AST": "1.0", "STL": "0.0", "BLK": "2.6", "TOV": "0.5", "PF": "4.2", "PTS": "4.2", "Awards": ""}{"Rk": "177", "Player": "Vincent Askew", "Age": "25", "Team": "GSW", "Pos": "SG", "G": "4", "GS": "0", "MP": "30", "FG": "1.2", "FGA": "9.6", "FG%": ".125", "3P": "0.0", "3PA": "0.0", "3P%": "", "2P": "1.2", "2PA": "9.6", "2P%": ".125", "eFG%": ".125", "FT": "0.0", "FTA": "0.0", "FT%": "", "ORB": "3.6", "DRB": "1.2", "TRB": "4.8", "AST": "6.0", "STL": "0.0", "BLK": "0.0", "TOV": "2.4", "PF": "3.6", "PTS": "2.4", "Awards": ""}{"Rk": "178", "Player": "Greg Dreiling", "Age": "29", "Team": "IND", "Pos": "C", "G": "1", "GS": "0", "MP": "3", "FG": "0.0", "FGA": "0.0", "FG%": "", "3P": "0.0", "3PA": "0.0", "3P%": "", "2P": "0.0", "2PA": "0.0", "2P%": "", "eFG%": "", "FT": "0.0", "FTA": "0.0", "FT%": "", "ORB": "0.0", "DRB": "0.0", "TRB": "0.0", "AST": "0.0", "STL": "0.0", "BLK": "0.0", "TOV": "0.0", "PF": "24.0", "PTS": "0.0", "Awards": ""}{"Rk": "179", "Player": "LeRon Ellis", "Age": "22", "Team": "LAC", "Pos": "C", "G": "1", "GS": "0", "MP": "2", "FG": "0.0", "FGA": "0.0", "FG%": "", "3P": "0.0", "3PA": "0.0", "3P%": "", "2P": "0.0", "2PA": "0.0", "2P%": "", "eFG%": "", "FT": "0.0", "FTA": "0.0", "FT%": "", "ORB": "0.0", "DRB": "0.0", "TRB": "0.0", "AST": "0.0", "STL": "0.0", "BLK": "0.0", "TOV": "0.0", "PF": "0.0", "PTS": "0.0", "Awards": ""}{"Rk": "180", "Player": "Sean Green", "Age": "21", "Team": "IND", "Pos": "SG", "G": "1", "GS": "0", "MP": "3", "FG": "0.0", "FGA": "0.0", "FG%": "", "3P": "0.0", "3PA": "0.0", "3P%": "", "2P": "0.0", "2PA": "0.0", "2P%": "", "eFG%": "", "FT": "0.0", "FTA": "0.0", "FT%": "", "ORB": "0.0", "DRB": "0.0", "TRB": "0.0", "AST": "0.0", "STL": "0.0", "BLK": "0.0", "TOV": "0.0", "PF": "0.0", "PTS": "0.0", "Awards": ""}{"Rk": "181", "Player": "Bo Kimble", "Age": "25", "Team": "LAC", "Pos": "SG", "G": "3", "GS": "0", "MP": "5", "FG": "0.0", "FGA": "7.2", "FG%": ".000", "3P": "0.0", "3PA": "0.0", "3P%": "", "2P": "0.0", "2PA": "7.2", "2P%": ".000", "eFG%": ".000", "FT": "0.0", "FTA": "0.0", "FT%": "", "ORB": "0.0", "DRB": "0.0", "TRB": "0.0", "AST": "7.2", "STL": "0.0", "BLK": "0.0", "TOV": "7.2", "PF": "14.4", "PTS": "0.0", "Awards": ""}{"Rk": "182", "Player": "Doug Lee", "Age": "27", "Team": "NJN", "Pos": "SG", "G": "2", "GS": "0", "MP": "6", "FG": "0.0", "FGA": "18.0", "FG%": ".000", "3P": "0.0", "3PA": "12.0", "3P%": ".000", "2P": "0.0", "2PA": "6.0", "2P%": ".000", "eFG%": ".000", "FT": "0.0", "FTA": "0.0", "FT%": "", "ORB": "0.0", "DRB": "0.0", "TRB": "0.0", "AST": "6.0", "STL": "0.0", "BLK": "6.0", "TOV": "0.0", "PF": "6.0", "PTS": "0.0", "Awards": ""}{"Rk": "183", "Player": "Tim McCormick", "Age": "29", "Team": "NYK", "Pos": "C", "G": "1", "GS": "0", "MP": "6", "FG": "0.0", "FGA": "12.0", "FG%": ".000", "3P": "0.0", "3PA": "0.0", "3P%": "", "2P": "0.0", "2PA": "12.0", "2P%": ".000", "eFG%": ".000", "FT": "0.0", "FTA": "0.0", "FT%": "", "ORB": "0.0", "DRB": "18.0", "TRB": "18.0", "AST": "0.0", "STL": "0.0", "BLK": "0.0", "TOV": "0.0", "PF": "6.0", "PTS": "0.0", "Awards": ""}{"Rk": "184", "Player": "Jon Sundvold", "Age": "30", "Team": "MIA", "Pos": "PG", "G": "1", "GS": "0", "MP": "2", "FG": "0.0", "FGA": "18.0", "FG%": ".000", "3P": "0.0", "3PA": "0.0", "3P%": "", "2P": "0.0", "2PA": "18.0", "2P%": ".000", "eFG%": ".000", "FT": "0.0", "FTA": "0.0", "FT%": "", "ORB": "0.0", "DRB": "0.0", "TRB": "0.0", "AST": "0.0", "STL": "0.0", "BLK": "0.0", "TOV": "0.0", "PF": "18.0", "PTS": "0.0", "Awards": ""}{"Rk": "185", "Player": "Kenny Williams", "Age": "22", "Team": "IND", "Pos": "SF", "G": "1", "GS": "0", "MP": "1", "FG": "0.0", "FGA": "0.0", "FG%": "", "3P": "0.0", "3PA": "0.0", "3P%": "", "2P": "0.0", "2PA": "0.0", "2P%": "", "eFG%": "", "FT": "0.0", "FTA": "0.0", "FT%": "", "ORB": "0.0", "DRB": "0.0", "TRB": "0.0", "AST": "0.0", "STL": "36.0", "BLK": "0.0", "TOV": "0.0", "PF": "0.0", "PTS": "0.0", "Awards": ""}{"Rk": "", "Player": "League Average", "Age": "", "Team": "", "Pos": "", "G": "", "GS": "", "MP": "", "FG": "", "FGA": "", "FG%": ".475", "3P": "", "3PA": "", "3P%": ".337", "2P": "", "2PA": "", "2P%": ".490", "eFG%": ".492", "FT": "", "FTA": "", "FT%": ".769", "ORB": "", "DRB": "", "TRB": "", "AST": "", "STL": "", "BLK": "", "TOV": "", "PF": "", "PTS": "", "Awards": ""}